{
    "data": [
        {
            "_isFinestGranularity": true,
            "capacity": {
                "battery storage": 0.0,
                "biomass": 58.0,
                "coal": 967.0,
                "gas": 548.0,
                "geothermal": 0.0,
                "hydro": 1121.0,
                "hydro storage": 180.0,
                "nuclear": 696.0,
                "oil": 0.0,
                "solar": 289.0,
                "unknown": null,
                "wind": 3.0
            },
            "co2intensity": 159.72,
            "co2intensityProduction": 182.25,
            "countryCode": "SI",
            "dischargeCo2Intensities": {
                "battery": 227.82342464167832,
                "hydro": 227.82342464167832
            },
            "dischargeCo2IntensitySources": {
                "battery": "electricityMap, 2021 average",
                "hydro": "electricityMap, 2021 average"
            },
            "estimationMethod": null,
            "exchange": {
                "AT": 669.0,
                "HR": 256.0,
                "IT-NO": -874.0
            },
            "exchangeCapacities": {},
            "exchangeCo2Intensities": {
                "AT": 105.0,
                "HR": 193.76,
                "IT-NO": 159.78
            },
            "fossilFuelRatio": 0.2212,
            "fossilFuelRatioProduction": 0.2089,
            "maxCapacity": 1121.0,
            "maxDischarge": 0,
            "maxExport": 874.0,
            "maxExportCapacity": null,
            "maxImport": 669.0,
            "maxImportCapacity": null,
            "maxProduction": 663.0,
            "maxStorage": 0,
            "maxStorageCapacity": 180.0,
            "price": {
                "currency": "EUR",
                "value": 288.01
            },
            "production": {
                "biomass": 19.0,
                "coal": 237.0,
                "gas": 22.0,
                "geothermal": null,
                "hydro": 232.0,
                "nuclear": 663.0,
                "oil": 0.0,
                "solar": 66.0,
                "unknown": null,
                "wind": 1.0
            },
            "productionCo2Intensities": {
                "biomass": 230,
                "coal": 820,
                "gas": 490,
                "geothermal": 38,
                "hydro": 24,
                "nuclear": 12,
                "oil": 650,
                "solar": 45,
                "unknown": 700,
                "wind": 11
            },
            "productionCo2IntensitySources": {
                "biomass": "IPCC 2014",
                "coal": "IPCC 2014",
                "gas": "IPCC 2014",
                "geothermal": "IPCC 2014",
                "hydro": "IPCC 2014",
                "nuclear": "IPCC 2014",
                "oil": "UK POST 2014",
                "solar": "IPCC 2014",
                "unknown": "assumes thermal (coal, gas, oil or biomass)",
                "wind": "IPCC 2014"
            },
            "renewableRatio": 0.4485,
            "renewableRatioProduction": 0.2565,
            "source": "entsoe.eu",
            "stateDatetime": "2022-07-08T09:00:00Z",
            "storage": {
                "battery": null,
                "hydro": -0.0
            },
            "totalCo2Discharge": 0.0,
            "totalCo2Export": 139647720.0,
            "totalCo2Import": 119847560.0,
            "totalCo2NetExchange": -19800160.0,
            "totalCo2Production": 225995000.0,
            "totalCo2Storage": 0,
            "totalConsumption": 1291.0,
            "totalDischarge": 0,
            "totalExport": 874.0,
            "totalImport": 925.0,
            "totalProduction": 1240.0,
            "totalStorage": 0
        },
        {
            "_isFinestGranularity": true,
            "capacity": {
                "battery storage": 0.0,
                "biomass": 58.0,
                "coal": 967.0,
                "gas": 548.0,
                "geothermal": 0.0,
                "hydro": 1121.0,
                "hydro storage": 180.0,
                "nuclear": 696.0,
                "oil": 0.0,
                "solar": 289.0,
                "unknown": null,
                "wind": 3.0
            },
            "co2intensity": 160.25,
            "co2intensityProduction": 199.09,
            "countryCode": "SI",
            "dischargeCo2Intensities": {
                "battery": 227.82342464167832,
                "hydro": 227.82342464167832
            },
            "dischargeCo2IntensitySources": {
                "battery": "electricityMap, 2021 average",
                "hydro": "electricityMap, 2021 average"
            },
            "estimationMethod": null,
            "exchange": {
                "AT": 906.25,
                "HR": 181.0,
                "IT-NO": -1034.0
            },
            "exchangeCapacities": {},
            "exchangeCo2Intensities": {
                "AT": 101.36,
                "HR": 178.72,
                "IT-NO": 160.29
            },
            "fossilFuelRatio": 0.2104,
            "fossilFuelRatioProduction": 0.2296,
            "maxCapacity": 1121.0,
            "maxDischarge": 0,
            "maxExport": 1034.0,
            "maxExportCapacity": null,
            "maxImport": 906.25,
            "maxImportCapacity": null,
            "maxProduction": 663.0,
            "maxStorage": 0,
            "maxStorageCapacity": 180.0,
            "price": {
                "currency": "EUR",
                "value": 253.98
            },
            "production": {
                "biomass": 19.0,
                "coal": 274.0,
                "gas": 22.0,
                "geothermal": null,
                "hydro": 244.0,
                "nuclear": 663.0,
                "oil": 0.0,
                "solar": 66.0,
                "unknown": null,
                "wind": 1.0
            },
            "productionCo2Intensities": {
                "biomass": 230,
                "coal": 820,
                "gas": 490,
                "geothermal": 38,
                "hydro": 24,
                "nuclear": 12,
                "oil": 650,
                "solar": 45,
                "unknown": 700,
                "wind": 11
            },
            "productionCo2IntensitySources": {
                "biomass": "IPCC 2014",
                "coal": "IPCC 2014",
                "gas": "IPCC 2014",
                "geothermal": "IPCC 2014",
                "hydro": "IPCC 2014",
                "nuclear": "IPCC 2014",
                "oil": "UK POST 2014",
                "solar": "IPCC 2014",
                "unknown": "assumes thermal (coal, gas, oil or biomass)",
                "wind": "IPCC 2014"
            },
            "renewableRatio": 0.4886,
            "renewableRatioProduction": 0.256,
            "source": "entsoe.eu",
            "stateDatetime": "2022-07-08T10:00:00Z",
            "storage": {
                "battery": null,
                "hydro": -0.0
            },
            "totalCo2Discharge": 0.0,
            "totalCo2Export": 165739860.0,
            "totalCo2Import": 124205820.0,
            "totalCo2NetExchange": -41534040.0,
            "totalCo2Production": 256623000.0,
            "totalCo2Storage": 0,
            "totalConsumption": 1342.25,
            "totalDischarge": 0,
            "totalExport": 1034.0,
            "totalImport": 1087.25,
            "totalProduction": 1289.0,
            "totalStorage": 0
        },
        {
            "_isFinestGranularity": true,
            "capacity": {
                "battery storage": 0.0,
                "biomass": 58.0,
                "coal": 967.0,
                "gas": 548.0,
                "geothermal": 0.0,
                "hydro": 1121.0,
                "hydro storage": 180.0,
                "nuclear": 696.0,
                "oil": 0.0,
                "solar": 289.0,
                "unknown": null,
                "wind": 3.0
            },
            "co2intensity": 154.94,
            "co2intensityProduction": 178.14,
            "countryCode": "SI",
            "dischargeCo2Intensities": {
                "battery": 227.82342464167832,
                "hydro": 227.82342464167832
            },
            "dischargeCo2IntensitySources": {
                "battery": "electricityMap, 2021 average",
                "hydro": "electricityMap, 2021 average"
            },
            "estimationMethod": null,
            "exchange": {
                "AT": 653.75,
                "HR": 296.0,
                "IT-NO": -988.0
            },
            "exchangeCapacities": {},
            "exchangeCo2Intensities": {
                "AT": 92.94,
                "HR": 191.48,
                "IT-NO": 154.94
            },
            "fossilFuelRatio": 0.21760000000000002,
            "fossilFuelRatioProduction": 0.203,
            "maxCapacity": 1121.0,
            "maxDischarge": 0,
            "maxExport": 988.0,
            "maxExportCapacity": null,
            "maxImport": 653.75,
            "maxImportCapacity": null,
            "maxProduction": 663.0,
            "maxStorage": 0,
            "maxStorageCapacity": 180.0,
            "price": {
                "currency": "EUR",
                "value": 245.53
            },
            "production": {
                "biomass": 19.0,
                "coal": 238.0,
                "gas": 22.0,
                "geothermal": null,
                "hydro": 252.0,
                "nuclear": 663.0,
                "oil": 0.0,
                "solar": 86.0,
                "unknown": null,
                "wind": 1.0
            },
            "productionCo2Intensities": {
                "biomass": 230,
                "coal": 820,
                "gas": 490,
                "geothermal": 38,
                "hydro": 24,
                "nuclear": 12,
                "oil": 650,
                "solar": 45,
                "unknown": 700,
                "wind": 11
            },
            "productionCo2IntensitySources": {
                "biomass": "IPCC 2014",
                "coal": "IPCC 2014",
                "gas": "IPCC 2014",
                "geothermal": "IPCC 2014",
                "hydro": "IPCC 2014",
                "nuclear": "IPCC 2014",
                "oil": "UK POST 2014",
                "solar": "IPCC 2014",
                "unknown": "assumes thermal (coal, gas, oil or biomass)",
                "wind": "IPCC 2014"
            },
            "renewableRatio": 0.4604,
            "renewableRatioProduction": 0.27949999999999997,
            "source": "entsoe.eu",
            "stateDatetime": "2022-07-08T11:00:00Z",
            "storage": {
                "battery": null,
                "hydro": -0.0
            },
            "totalCo2Discharge": 0.0,
            "totalCo2Export": 153080720.0,
            "totalCo2Import": 117437605.0,
            "totalCo2NetExchange": -35643115.0,
            "totalCo2Production": 228195000.0,
            "totalCo2Storage": 0,
            "totalConsumption": 1242.75,
            "totalDischarge": 0,
            "totalExport": 988.0,
            "totalImport": 949.75,
            "totalProduction": 1281.0,
            "totalStorage": 0
        },
        {
            "_isFinestGranularity": true,
            "capacity": {
                "battery storage": 0.0,
                "biomass": 58.0,
                "coal": 967.0,
                "gas": 548.0,
                "geothermal": 0.0,
                "hydro": 1121.0,
                "hydro storage": 180.0,
                "nuclear": 696.0,
                "oil": 0.0,
                "solar": 289.0,
                "unknown": null,
                "wind": 3.0
            },
            "co2intensity": 158.68,
            "co2intensityProduction": 178.43,
            "countryCode": "SI",
            "dischargeCo2Intensities": {
                "battery": 227.82342464167832,
                "hydro": 227.82342464167832
            },
            "dischargeCo2IntensitySources": {
                "battery": "electricityMap, 2021 average",
                "hydro": "electricityMap, 2021 average"
            },
            "estimationMethod": null,
            "exchange": {
                "AT": 453.25,
                "HR": 252.0,
                "IT-NO": -893.0
            },
            "exchangeCapacities": {},
            "exchangeCo2Intensities": {
                "AT": 90.4,
                "HR": 191.37,
                "IT-NO": 161.35
            },
            "fossilFuelRatio": 0.2183,
            "fossilFuelRatioProduction": 0.20309999999999997,
            "maxCapacity": 1121.0,
            "maxDischarge": 0,
            "maxExport": 893.0,
            "maxExportCapacity": null,
            "maxImport": 453.25,
            "maxImportCapacity": null,
            "maxProduction": 663.0,
            "maxStorage": 0,
            "maxStorageCapacity": 180.0,
            "price": {
                "currency": "EUR",
                "value": 237.86
            },
            "production": {
                "biomass": 19.0,
                "coal": 236.0,
                "gas": 22.0,
                "geothermal": null,
                "hydro": 230.0,
                "nuclear": 663.0,
                "oil": 0.0,
                "solar": 99.0,
                "unknown": null,
                "wind": 1.0
            },
            "productionCo2Intensities": {
                "biomass": 230,
                "coal": 820,
                "gas": 490,
                "geothermal": 38,
                "hydro": 24,
                "nuclear": 12,
                "oil": 650,
                "solar": 45,
                "unknown": 700,
                "wind": 11
            },
            "productionCo2IntensitySources": {
                "biomass": "IPCC 2014",
                "coal": "IPCC 2014",
                "gas": "IPCC 2014",
                "geothermal": "IPCC 2014",
                "hydro": "IPCC 2014",
                "nuclear": "IPCC 2014",
                "oil": "UK POST 2014",
                "solar": "IPCC 2014",
                "unknown": "assumes thermal (coal, gas, oil or biomass)",
                "wind": "IPCC 2014"
            },
            "renewableRatio": 0.4315,
            "renewableRatioProduction": 0.2748,
            "source": "entsoe.eu",
            "stateDatetime": "2022-07-08T12:00:00Z",
            "storage": {
                "battery": null,
                "hydro": -0.0
            },
            "totalCo2Discharge": 0.0,
            "totalCo2Export": 144085550.0,
            "totalCo2Import": 89199040.0,
            "totalCo2NetExchange": -54886510.0,
            "totalCo2Production": 226612000.0,
            "totalCo2Storage": 0,
            "totalConsumption": 1082.25,
            "totalDischarge": 0,
            "totalExport": 893.0,
            "totalImport": 705.25,
            "totalProduction": 1270.0,
            "totalStorage": 0
        },
        {
            "_isFinestGranularity": true,
            "capacity": {
                "battery storage": 0.0,
                "biomass": 58.0,
                "coal": 967.0,
                "gas": 548.0,
                "geothermal": 0.0,
                "hydro": 1121.0,
                "hydro storage": 180.0,
                "nuclear": 696.0,
                "oil": 0.0,
                "solar": 289.0,
                "unknown": null,
                "wind": 3.0
            },
            "co2intensity": 168.17,
            "co2intensityProduction": 189.29,
            "countryCode": "SI",
            "dischargeCo2Intensities": {
                "battery": 227.82342464167832,
                "hydro": 227.82342464167832
            },
            "dischargeCo2IntensitySources": {
                "battery": "electricityMap, 2021 average",
                "hydro": "electricityMap, 2021 average"
            },
            "estimationMethod": null,
            "exchange": {
                "AT": 421.0,
                "HR": 322.0,
                "IT-NO": -881.0
            },
            "exchangeCapacities": {},
            "exchangeCo2Intensities": {
                "AT": 87.23,
                "HR": 203.21,
                "IT-NO": 171.0
            },
            "fossilFuelRatio": 0.24170000000000003,
            "fossilFuelRatioProduction": 0.218,
            "maxCapacity": 1121.0,
            "maxDischarge": 0,
            "maxExport": 881.0,
            "maxExportCapacity": null,
            "maxImport": 421.0,
            "maxImportCapacity": null,
            "maxProduction": 663.0,
            "maxStorage": 0,
            "maxStorageCapacity": 180.0,
            "price": {
                "currency": "EUR",
                "value": 216.27
            },
            "production": {
                "biomass": 19.0,
                "coal": 238.0,
                "gas": 23.0,
                "geothermal": null,
                "hydro": 170.0,
                "nuclear": 663.0,
                "oil": 0.0,
                "solar": 83.0,
                "unknown": null,
                "wind": 1.0
            },
            "productionCo2Intensities": {
                "biomass": 230,
                "coal": 820,
                "gas": 490,
                "geothermal": 38,
                "hydro": 24,
                "nuclear": 12,
                "oil": 650,
                "solar": 45,
                "unknown": 700,
                "wind": 11
            },
            "productionCo2IntensitySources": {
                "biomass": "IPCC 2014",
                "coal": "IPCC 2014",
                "gas": "IPCC 2014",
                "geothermal": "IPCC 2014",
                "hydro": "IPCC 2014",
                "nuclear": "IPCC 2014",
                "oil": "UK POST 2014",
                "solar": "IPCC 2014",
                "unknown": "assumes thermal (coal, gas, oil or biomass)",
                "wind": "IPCC 2014"
            },
            "renewableRatio": 0.40159999999999996,
            "renewableRatioProduction": 0.2281,
            "source": "entsoe.eu",
            "stateDatetime": "2022-07-08T13:00:00Z",
            "storage": {
                "battery": null,
                "hydro": -0.0
            },
            "totalCo2Discharge": 0.0,
            "totalCo2Export": 150651000.0,
            "totalCo2Import": 102157450.0,
            "totalCo2NetExchange": -48493550.0,
            "totalCo2Production": 226582000.0,
            "totalCo2Storage": 0,
            "totalConsumption": 1059.0,
            "totalDischarge": 0,
            "totalExport": 881.0,
            "totalImport": 743.0,
            "totalProduction": 1197.0,
            "totalStorage": 0
        },
        {
            "_isFinestGranularity": true,
            "capacity": {
                "battery storage": 0.0,
                "biomass": 58.0,
                "coal": 967.0,
                "gas": 548.0,
                "geothermal": 0.0,
                "hydro": 1121.0,
                "hydro storage": 180.0,
                "nuclear": 696.0,
                "oil": 0.0,
                "solar": 289.0,
                "unknown": null,
                "wind": 3.0
            },
            "co2intensity": 167.34,
            "co2intensityProduction": 187.36,
            "countryCode": "SI",
            "dischargeCo2Intensities": {
                "battery": 227.82342464167832,
                "hydro": 227.82342464167832
            },
            "dischargeCo2IntensitySources": {
                "battery": "electricityMap, 2021 average",
                "hydro": "electricityMap, 2021 average"
            },
            "estimationMethod": null,
            "exchange": {
                "AT": 398.75,
                "HR": 284.0,
                "IT-NO": -852.0
            },
            "exchangeCapacities": {},
            "exchangeCo2Intensities": {
                "AT": 92.45,
                "HR": 194.4,
                "IT-NO": 169.74
            },
            "fossilFuelRatio": 0.23929999999999998,
            "fossilFuelRatioProduction": 0.2157,
            "maxCapacity": 1121.0,
            "maxDischarge": 0,
            "maxExport": 852.0,
            "maxExportCapacity": null,
            "maxImport": 398.75,
            "maxImportCapacity": null,
            "maxProduction": 663.0,
            "maxStorage": 0,
            "maxStorageCapacity": 180.0,
            "price": {
                "currency": "EUR",
                "value": 240.44
            },
            "production": {
                "biomass": 19.0,
                "coal": 238.0,
                "gas": 23.0,
                "geothermal": null,
                "hydro": 192.0,
                "nuclear": 663.0,
                "oil": 0.0,
                "solar": 74.0,
                "unknown": null,
                "wind": 1.0
            },
            "productionCo2Intensities": {
                "biomass": 230,
                "coal": 820,
                "gas": 490,
                "geothermal": 38,
                "hydro": 24,
                "nuclear": 12,
                "oil": 650,
                "solar": 45,
                "unknown": 700,
                "wind": 11
            },
            "productionCo2IntensitySources": {
                "biomass": "IPCC 2014",
                "coal": "IPCC 2014",
                "gas": "IPCC 2014",
                "geothermal": "IPCC 2014",
                "hydro": "IPCC 2014",
                "nuclear": "IPCC 2014",
                "oil": "UK POST 2014",
                "solar": "IPCC 2014",
                "unknown": "assumes thermal (coal, gas, oil or biomass)",
                "wind": "IPCC 2014"
            },
            "renewableRatio": 0.39549999999999996,
            "renewableRatioProduction": 0.2364,
            "source": "entsoe.eu",
            "stateDatetime": "2022-07-08T14:00:00Z",
            "storage": {
                "battery": null,
                "hydro": -0.0
            },
            "totalCo2Discharge": 0.0,
            "totalCo2Export": 144618480.0,
            "totalCo2Import": 92074037.5,
            "totalCo2NetExchange": -52544442.5,
            "totalCo2Production": 226705000.0,
            "totalCo2Storage": 0,
            "totalConsumption": 1040.75,
            "totalDischarge": 0,
            "totalExport": 852.0,
            "totalImport": 682.75,
            "totalProduction": 1210.0,
            "totalStorage": 0
        },
        {
            "_isFinestGranularity": true,
            "capacity": {
                "battery storage": 0.0,
                "biomass": 58.0,
                "coal": 967.0,
                "gas": 548.0,
                "geothermal": 0.0,
                "hydro": 1121.0,
                "hydro storage": 180.0,
                "nuclear": 696.0,
                "oil": 0.0,
                "solar": 289.0,
                "unknown": null,
                "wind": 3.0
            },
            "co2intensity": 163.04,
            "co2intensityProduction": 167.3,
            "countryCode": "SI",
            "dischargeCo2Intensities": {
                "battery": 227.82342464167832,
                "hydro": 227.82342464167832
            },
            "dischargeCo2IntensitySources": {
                "battery": "electricityMap, 2021 average",
                "hydro": "electricityMap, 2021 average"
            },
            "estimationMethod": null,
            "exchange": {
                "AT": 394.5,
                "HR": 381.0,
                "IT-NO": -937.0
            },
            "exchangeCapacities": {},
            "exchangeCo2Intensities": {
                "AT": 90.79,
                "HR": 222.35,
                "IT-NO": 163.05
            },
            "fossilFuelRatio": 0.244,
            "fossilFuelRatioProduction": 0.1898,
            "maxCapacity": 1121.0,
            "maxDischarge": 0,
            "maxExport": 937.0,
            "maxExportCapacity": null,
            "maxImport": 394.5,
            "maxImportCapacity": null,
            "maxProduction": 663.0,
            "maxStorage": 0,
            "maxStorageCapacity": 180.0,
            "price": {
                "currency": "EUR",
                "value": 266.71
            },
            "production": {
                "biomass": 19.0,
                "coal": 240.0,
                "gas": 24.0,
                "geothermal": null,
                "hydro": 389.0,
                "nuclear": 663.0,
                "oil": 0.0,
                "solar": 55.0,
                "unknown": null,
                "wind": 1.0
            },
            "productionCo2Intensities": {
                "biomass": 230,
                "coal": 820,
                "gas": 490,
                "geothermal": 38,
                "hydro": 24,
                "nuclear": 12,
                "oil": 650,
                "solar": 45,
                "unknown": 700,
                "wind": 11
            },
            "productionCo2IntensitySources": {
                "biomass": "IPCC 2014",
                "coal": "IPCC 2014",
                "gas": "IPCC 2014",
                "geothermal": "IPCC 2014",
                "hydro": "IPCC 2014",
                "nuclear": "IPCC 2014",
                "oil": "UK POST 2014",
                "solar": "IPCC 2014",
                "unknown": "assumes thermal (coal, gas, oil or biomass)",
                "wind": "IPCC 2014"
            },
            "renewableRatio": 0.4325,
            "renewableRatioProduction": 0.3336,
            "source": "entsoe.eu",
            "stateDatetime": "2022-07-08T15:00:00Z",
            "storage": {
                "battery": null,
                "hydro": -0.0
            },
            "totalCo2Discharge": 0.0,
            "totalCo2Export": 152777850.0,
            "totalCo2Import": 120532005.0,
            "totalCo2NetExchange": -32245845.0,
            "totalCo2Production": 232708000.0,
            "totalCo2Storage": 0,
            "totalConsumption": 1229.5,
            "totalDischarge": 0,
            "totalExport": 937.0,
            "totalImport": 775.5,
            "totalProduction": 1391.0,
            "totalStorage": 0
        },
        {
            "_isFinestGranularity": true,
            "capacity": {
                "battery storage": 0.0,
                "biomass": 58.0,
                "coal": 967.0,
                "gas": 548.0,
                "geothermal": 0.0,
                "hydro": 1121.0,
                "hydro storage": 180.0,
                "nuclear": 696.0,
                "oil": 0.0,
                "solar": 289.0,
                "unknown": null,
                "wind": 3.0
            },
            "co2intensity": 174.1,
            "co2intensityProduction": 170.19,
            "countryCode": "SI",
            "dischargeCo2Intensities": {
                "battery": 227.82342464167832,
                "hydro": 227.82342464167832
            },
            "dischargeCo2IntensitySources": {
                "battery": "electricityMap, 2021 average",
                "hydro": "electricityMap, 2021 average"
            },
            "estimationMethod": null,
            "exchange": {
                "AT": 303.75,
                "HR": 467.0,
                "IT-NO": -970.0
            },
            "exchangeCapacities": {},
            "exchangeCo2Intensities": {
                "AT": 80.77,
                "HR": 247.55,
                "IT-NO": 174.11
            },
            "fossilFuelRatio": 0.2639,
            "fossilFuelRatioProduction": 0.193,
            "maxCapacity": 1121.0,
            "maxDischarge": 0,
            "maxExport": 970.0,
            "maxExportCapacity": null,
            "maxImport": 467.0,
            "maxImportCapacity": null,
            "maxProduction": 663.0,
            "maxStorage": 0,
            "maxStorageCapacity": 180.0,
            "price": {
                "currency": "EUR",
                "value": 324.62
            },
            "production": {
                "biomass": 19.0,
                "coal": 269.0,
                "gas": 24.0,
                "geothermal": null,
                "hydro": 509.0,
                "nuclear": 663.0,
                "oil": 0.0,
                "solar": 32.0,
                "unknown": null,
                "wind": 2.0
            },
            "productionCo2Intensities": {
                "biomass": 230,
                "coal": 820,
                "gas": 490,
                "geothermal": 38,
                "hydro": 24,
                "nuclear": 12,
                "oil": 650,
                "solar": 45,
                "unknown": 700,
                "wind": 11
            },
            "productionCo2IntensitySources": {
                "biomass": "IPCC 2014",
                "coal": "IPCC 2014",
                "gas": "IPCC 2014",
                "geothermal": "IPCC 2014",
                "hydro": "IPCC 2014",
                "nuclear": "IPCC 2014",
                "oil": "UK POST 2014",
                "solar": "IPCC 2014",
                "unknown": "assumes thermal (coal, gas, oil or biomass)",
                "wind": "IPCC 2014"
            },
            "renewableRatio": 0.4322,
            "renewableRatioProduction": 0.37020000000000003,
            "source": "entsoe.eu",
            "stateDatetime": "2022-07-08T16:00:00Z",
            "storage": {
                "battery": null,
                "hydro": -0.0
            },
            "totalCo2Discharge": 0.0,
            "totalCo2Export": 168886700.0,
            "totalCo2Import": 140139737.5,
            "totalCo2NetExchange": -28746962.5,
            "totalCo2Production": 258344000.0,
            "totalCo2Storage": 0,
            "totalConsumption": 1318.75,
            "totalDischarge": 0,
            "totalExport": 970.0,
            "totalImport": 770.75,
            "totalProduction": 1518.0,
            "totalStorage": 0
        },
        {
            "_isFinestGranularity": true,
            "capacity": {
                "battery storage": 0.0,
                "biomass": 58.0,
                "coal": 967.0,
                "gas": 548.0,
                "geothermal": 0.0,
                "hydro": 1121.0,
                "hydro storage": 180.0,
                "nuclear": 696.0,
                "oil": 0.0,
                "solar": 289.0,
                "unknown": null,
                "wind": 3.0
            },
            "co2intensity": 157.8,
            "co2intensityProduction": 166.41,
            "countryCode": "SI",
            "dischargeCo2Intensities": {
                "battery": 227.82342464167832,
                "hydro": 227.82342464167832
            },
            "dischargeCo2IntensitySources": {
                "battery": "electricityMap, 2021 average",
                "hydro": "electricityMap, 2021 average"
            },
            "estimationMethod": null,
            "exchange": {
                "AT": 404.5,
                "HR": 281.0,
                "IT-NO": -729.0
            },
            "exchangeCapacities": {},
            "exchangeCo2Intensities": {
                "AT": 72.17,
                "HR": 237.33,
                "IT-NO": 159.4
            },
            "fossilFuelRatio": 0.21600000000000003,
            "fossilFuelRatioProduction": 0.1881,
            "maxCapacity": 1121.0,
            "maxDischarge": 0,
            "maxExport": 729.0,
            "maxExportCapacity": null,
            "maxImport": 404.5,
            "maxImportCapacity": null,
            "maxProduction": 664.0,
            "maxStorage": 0,
            "maxStorageCapacity": 180.0,
            "price": {
                "currency": "EUR",
                "value": 391.0
            },
            "production": {
                "biomass": 19.0,
                "coal": 271.0,
                "gas": 23.0,
                "geothermal": null,
                "hydro": 573.0,
                "nuclear": 664.0,
                "oil": 0.0,
                "solar": 11.0,
                "unknown": null,
                "wind": 2.0
            },
            "productionCo2Intensities": {
                "biomass": 230,
                "coal": 820,
                "gas": 490,
                "geothermal": 38,
                "hydro": 24,
                "nuclear": 12,
                "oil": 650,
                "solar": 45,
                "unknown": 700,
                "wind": 11
            },
            "productionCo2IntensitySources": {
                "biomass": "IPCC 2014",
                "coal": "IPCC 2014",
                "gas": "IPCC 2014",
                "geothermal": "IPCC 2014",
                "hydro": "IPCC 2014",
                "nuclear": "IPCC 2014",
                "oil": "UK POST 2014",
                "solar": "IPCC 2014",
                "unknown": "assumes thermal (coal, gas, oil or biomass)",
                "wind": "IPCC 2014"
            },
            "renewableRatio": 0.4796,
            "renewableRatioProduction": 0.3871,
            "source": "entsoe.eu",
            "stateDatetime": "2022-07-08T17:00:00Z",
            "storage": {
                "battery": null,
                "hydro": -0.0
            },
            "totalCo2Discharge": 0.0,
            "totalCo2Export": 116202600.0,
            "totalCo2Import": 95882495.0,
            "totalCo2NetExchange": -20320105.0,
            "totalCo2Production": 260097000.0,
            "totalCo2Storage": 0,
            "totalConsumption": 1519.5,
            "totalDischarge": 0,
            "totalExport": 729.0,
            "totalImport": 685.5,
            "totalProduction": 1563.0,
            "totalStorage": 0
        },
        {
            "_isFinestGranularity": true,
            "capacity": {
                "battery storage": 0.0,
                "biomass": 58.0,
                "coal": 967.0,
                "gas": 548.0,
                "geothermal": 0.0,
                "hydro": 1121.0,
                "hydro storage": 180.0,
                "nuclear": 696.0,
                "oil": 0.0,
                "solar": 289.0,
                "unknown": null,
                "wind": 3.0
            },
            "co2intensity": 165.84,
            "co2intensityProduction": 176.2,
            "countryCode": "SI",
            "dischargeCo2Intensities": {
                "battery": 227.82342464167832,
                "hydro": 227.82342464167832
            },
            "dischargeCo2IntensitySources": {
                "battery": "electricityMap, 2021 average",
                "hydro": "electricityMap, 2021 average"
            },
            "estimationMethod": null,
            "exchange": {
                "AT": 452.25,
                "HR": 189.0,
                "IT-NO": -954.0
            },
            "exchangeCapacities": {},
            "exchangeCo2Intensities": {
                "AT": 76.85,
                "HR": 237.28,
                "IT-NO": 165.84
            },
            "fossilFuelRatio": 0.19149999999999998,
            "fossilFuelRatioProduction": 0.1821,
            "maxCapacity": 1121.0,
            "maxDischarge": 161.0,
            "maxExport": 954.0,
            "maxExportCapacity": null,
            "maxImport": 452.25,
            "maxImportCapacity": null,
            "maxProduction": 664.0,
            "maxStorage": 0,
            "maxStorageCapacity": 180.0,
            "price": {
                "currency": "EUR",
                "value": 412.44
            },
            "production": {
                "biomass": 19.0,
                "coal": 301.0,
                "gas": 23.0,
                "geothermal": null,
                "hydro": 608.0,
                "nuclear": 664.0,
                "oil": 0.0,
                "solar": 1.0,
                "unknown": null,
                "wind": 2.0
            },
            "productionCo2Intensities": {
                "biomass": 230,
                "coal": 820,
                "gas": 490,
                "geothermal": 38,
                "hydro": 24,
                "nuclear": 12,
                "oil": 650,
                "solar": 45,
                "unknown": 700,
                "wind": 11
            },
            "productionCo2IntensitySources": {
                "biomass": "IPCC 2014",
                "coal": "IPCC 2014",
                "gas": "IPCC 2014",
                "geothermal": "IPCC 2014",
                "hydro": "IPCC 2014",
                "nuclear": "IPCC 2014",
                "oil": "UK POST 2014",
                "solar": "IPCC 2014",
                "unknown": "assumes thermal (coal, gas, oil or biomass)",
                "wind": "IPCC 2014"
            },
            "renewableRatio": 0.5272,
            "renewableRatioProduction": 0.4446,
            "source": "entsoe.eu",
            "stateDatetime": "2022-07-08T18:00:00Z",
            "storage": {
                "battery": null,
                "hydro": -161.0
            },
            "totalCo2Discharge": 36679571.36731021,
            "totalCo2Export": 158211360.0,
            "totalCo2Import": 79601332.5,
            "totalCo2NetExchange": -78610027.5,
            "totalCo2Production": 285087000.0,
            "totalCo2Storage": 0,
            "totalConsumption": 1466.25,
            "totalDischarge": 161.0,
            "totalExport": 954.0,
            "totalImport": 641.25,
            "totalProduction": 1618.0,
            "totalStorage": 0
        },
        {
            "_isFinestGranularity": true,
            "capacity": {
                "battery storage": 0.0,
                "biomass": 58.0,
                "coal": 967.0,
                "gas": 548.0,
                "geothermal": 0.0,
                "hydro": 1121.0,
                "hydro storage": 180.0,
                "nuclear": 696.0,
                "oil": 0.0,
                "solar": 289.0,
                "unknown": null,
                "wind": 3.0
            },
            "co2intensity": 180.3,
            "co2intensityProduction": 190.24,
            "countryCode": "SI",
            "dischargeCo2Intensities": {
                "battery": 227.82342464167832,
                "hydro": 227.82342464167832
            },
            "dischargeCo2IntensitySources": {
                "battery": "electricityMap, 2021 average",
                "hydro": "electricityMap, 2021 average"
            },
            "estimationMethod": null,
            "exchange": {
                "AT": 438.25,
                "HR": 277.0,
                "IT-NO": -989.0
            },
            "exchangeCapacities": {},
            "exchangeCo2Intensities": {
                "AT": 80.07,
                "HR": 258.56,
                "IT-NO": 180.33
            },
            "fossilFuelRatio": 0.2211,
            "fossilFuelRatioProduction": 0.19879999999999998,
            "maxCapacity": 1121.0,
            "maxDischarge": 154.0,
            "maxExport": 989.0,
            "maxExportCapacity": null,
            "maxImport": 438.25,
            "maxImportCapacity": null,
            "maxProduction": 664.0,
            "maxStorage": 0,
            "maxStorageCapacity": 180.0,
            "price": {
                "currency": "EUR",
                "value": 422.86
            },
            "production": {
                "biomass": 19.0,
                "coal": 305.0,
                "gas": 25.0,
                "geothermal": null,
                "hydro": 491.0,
                "nuclear": 664.0,
                "oil": 0.0,
                "solar": 0.0,
                "unknown": null,
                "wind": 2.0
            },
            "productionCo2Intensities": {
                "biomass": 230,
                "coal": 820,
                "gas": 490,
                "geothermal": 38,
                "hydro": 24,
                "nuclear": 12,
                "oil": 650,
                "solar": 45,
                "unknown": 700,
                "wind": 11
            },
            "productionCo2IntensitySources": {
                "biomass": "IPCC 2014",
                "coal": "IPCC 2014",
                "gas": "IPCC 2014",
                "geothermal": "IPCC 2014",
                "hydro": "IPCC 2014",
                "nuclear": "IPCC 2014",
                "oil": "UK POST 2014",
                "solar": "IPCC 2014",
                "unknown": "assumes thermal (coal, gas, oil or biomass)",
                "wind": "IPCC 2014"
            },
            "renewableRatio": 0.4917,
            "renewableRatioProduction": 0.4012,
            "source": "entsoe.eu",
            "stateDatetime": "2022-07-08T19:00:00Z",
            "storage": {
                "battery": null,
                "hydro": -154.0
            },
            "totalCo2Discharge": 35084807.39481846,
            "totalCo2Export": 178346370.0,
            "totalCo2Import": 106711797.5,
            "totalCo2NetExchange": -71634572.5,
            "totalCo2Production": 286494000.0,
            "totalCo2Storage": 0,
            "totalConsumption": 1386.25,
            "totalDischarge": 154.0,
            "totalExport": 989.0,
            "totalImport": 715.25,
            "totalProduction": 1506.0,
            "totalStorage": 0
        },
        {
            "_isFinestGranularity": true,
            "capacity": {
                "battery storage": 0.0,
                "biomass": 58.0,
                "coal": 967.0,
                "gas": 548.0,
                "geothermal": 0.0,
                "hydro": 1121.0,
                "hydro storage": 180.0,
                "nuclear": 696.0,
                "oil": 0.0,
                "solar": 289.0,
                "unknown": null,
                "wind": 3.0
            },
            "co2intensity": 171.13,
            "co2intensityProduction": 183.28,
            "countryCode": "SI",
            "dischargeCo2Intensities": {
                "battery": 227.82342464167832,
                "hydro": 227.82342464167832
            },
            "dischargeCo2IntensitySources": {
                "battery": "electricityMap, 2021 average",
                "hydro": "electricityMap, 2021 average"
            },
            "estimationMethod": null,
            "exchange": {
                "AT": 304.25,
                "HR": 143.0,
                "IT-NO": -448.0
            },
            "exchangeCapacities": {},
            "exchangeCo2Intensities": {
                "AT": 80.28,
                "HR": 231.44,
                "IT-NO": 174.78
            },
            "fossilFuelRatio": 0.205,
            "fossilFuelRatioProduction": 0.19699999999999998,
            "maxCapacity": 1121.0,
            "maxDischarge": 98.0,
            "maxExport": 448.0,
            "maxExportCapacity": null,
            "maxImport": 304.25,
            "maxImportCapacity": null,
            "maxProduction": 665.0,
            "maxStorage": 0,
            "maxStorageCapacity": 180.0,
            "price": {
                "currency": "EUR",
                "value": 419.65
            },
            "production": {
                "biomass": 19.0,
                "coal": 239.0,
                "gas": 25.0,
                "geothermal": null,
                "hydro": 294.0,
                "nuclear": 665.0,
                "oil": 0.0,
                "solar": 0.0,
                "unknown": null,
                "wind": 0.0
            },
            "productionCo2Intensities": {
                "biomass": 230,
                "coal": 820,
                "gas": 490,
                "geothermal": 38,
                "hydro": 24,
                "nuclear": 12,
                "oil": 650,
                "solar": 45,
                "unknown": 700,
                "wind": 11
            },
            "productionCo2IntensitySources": {
                "biomass": "IPCC 2014",
                "coal": "IPCC 2014",
                "gas": "IPCC 2014",
                "geothermal": "IPCC 2014",
                "hydro": "IPCC 2014",
                "nuclear": "IPCC 2014",
                "oil": "UK POST 2014",
                "solar": "IPCC 2014",
                "unknown": "assumes thermal (coal, gas, oil or biomass)",
                "wind": "IPCC 2014"
            },
            "renewableRatio": 0.4165,
            "renewableRatioProduction": 0.30670000000000003,
            "source": "entsoe.eu",
            "stateDatetime": "2022-07-08T20:00:00Z",
            "storage": {
                "battery": null,
                "hydro": -98.0
            },
            "totalCo2Discharge": 22326695.614884473,
            "totalCo2Export": 78301440.0,
            "totalCo2Import": 57521110.0,
            "totalCo2NetExchange": -20780330.0,
            "totalCo2Production": 227636000.0,
            "totalCo2Storage": 0,
            "totalConsumption": 1339.25,
            "totalDischarge": 98.0,
            "totalExport": 448.0,
            "totalImport": 447.25,
            "totalProduction": 1242.0,
            "totalStorage": 0
        },
        {
            "_isFinestGranularity": true,
            "capacity": {
                "battery storage": 0.0,
                "biomass": 58.0,
                "coal": 967.0,
                "gas": 548.0,
                "geothermal": 0.0,
                "hydro": 1121.0,
                "hydro storage": 180.0,
                "nuclear": 696.0,
                "oil": 0.0,
                "solar": 289.0,
                "unknown": null,
                "wind": 3.0
            },
            "co2intensity": 206.49,
            "co2intensityProduction": 185.53,
            "countryCode": "SI",
            "dischargeCo2Intensities": {
                "battery": 227.82342464167832,
                "hydro": 227.82342464167832
            },
            "dischargeCo2IntensitySources": {
                "battery": "electricityMap, 2021 average",
                "hydro": "electricityMap, 2021 average"
            },
            "estimationMethod": null,
            "exchange": {
                "AT": 79.75,
                "HR": 564.0,
                "IT-NO": -248.0
            },
            "exchangeCapacities": {},
            "exchangeCo2Intensities": {
                "AT": 80.39,
                "HR": 266.68,
                "IT-NO": 207.34
            },
            "fossilFuelRatio": 0.34259999999999996,
            "fossilFuelRatioProduction": 0.2164,
            "maxCapacity": 1121.0,
            "maxDischarge": 1.0,
            "maxExport": 248.0,
            "maxExportCapacity": null,
            "maxImport": 564.0,
            "maxImportCapacity": null,
            "maxProduction": 665.0,
            "maxStorage": 0,
            "maxStorageCapacity": 180.0,
            "price": {
                "currency": "EUR",
                "value": 375.24
            },
            "production": {
                "biomass": 19.0,
                "coal": 220.0,
                "gas": 25.0,
                "geothermal": null,
                "hydro": 201.0,
                "nuclear": 665.0,
                "oil": 0.0,
                "solar": 0.0,
                "unknown": null,
                "wind": 1.0
            },
            "productionCo2Intensities": {
                "biomass": 230,
                "coal": 820,
                "gas": 490,
                "geothermal": 38,
                "hydro": 24,
                "nuclear": 12,
                "oil": 650,
                "solar": 45,
                "unknown": 700,
                "wind": 11
            },
            "productionCo2IntensitySources": {
                "biomass": "IPCC 2014",
                "coal": "IPCC 2014",
                "gas": "IPCC 2014",
                "geothermal": "IPCC 2014",
                "hydro": "IPCC 2014",
                "nuclear": "IPCC 2014",
                "oil": "UK POST 2014",
                "solar": "IPCC 2014",
                "unknown": "assumes thermal (coal, gas, oil or biomass)",
                "wind": "IPCC 2014"
            },
            "renewableRatio": 0.2657,
            "renewableRatioProduction": 0.1961,
            "source": "entsoe.eu",
            "stateDatetime": "2022-07-08T21:00:00Z",
            "storage": {
                "battery": null,
                "hydro": -1.0
            },
            "totalCo2Discharge": 227823.4246416783,
            "totalCo2Export": 51420320.0,
            "totalCo2Import": 156818622.5,
            "totalCo2NetExchange": 105398302.5,
            "totalCo2Production": 209835000.0,
            "totalCo2Storage": 0,
            "totalConsumption": 1527.75,
            "totalDischarge": 1.0,
            "totalExport": 248.0,
            "totalImport": 643.75,
            "totalProduction": 1131.0,
            "totalStorage": 0
        },
        {
            "_isFinestGranularity": true,
            "capacity": {
                "battery storage": 0.0,
                "biomass": 58.0,
                "coal": 967.0,
                "gas": 548.0,
                "geothermal": 0.0,
                "hydro": 1121.0,
                "hydro storage": 180.0,
                "nuclear": 696.0,
                "oil": 0.0,
                "solar": 289.0,
                "unknown": null,
                "wind": 3.0
            },
            "co2intensity": 77.8,
            "co2intensityProduction": 29.95,
            "countryCode": "SI",
            "dischargeCo2Intensities": {
                "battery": 227.82342464167832,
                "hydro": 227.82342464167832
            },
            "dischargeCo2IntensitySources": {
                "battery": "electricityMap, 2021 average",
                "hydro": "electricityMap, 2021 average"
            },
            "estimationMethod": null,
            "exchange": {
                "AT": 422.75,
                "HR": 416.0,
                "IT-NO": -813.0
            },
            "exchangeCapacities": {},
            "exchangeCo2Intensities": {
                "AT": 81.4,
                "HR": 198.43,
                "IT-NO": 77.65
            },
            "fossilFuelRatio": 0.1413,
            "fossilFuelRatioProduction": 0.0212,
            "maxCapacity": 1121.0,
            "maxDischarge": 0,
            "maxExport": 813.0,
            "maxExportCapacity": null,
            "maxImport": 422.75,
            "maxImportCapacity": null,
            "maxProduction": 665.0,
            "maxStorage": 0,
            "maxStorageCapacity": 180.0,
            "price": {
                "currency": "EUR",
                "value": 350.0
            },
            "production": {
                "biomass": 18.0,
                "coal": 0.0,
                "gas": 23.0,
                "geothermal": null,
                "hydro": 377.0,
                "nuclear": 665.0,
                "oil": 0.0,
                "solar": 0.0,
                "unknown": null,
                "wind": 0.0
            },
            "productionCo2Intensities": {
                "biomass": 230,
                "coal": 820,
                "gas": 490,
                "geothermal": 38,
                "hydro": 24,
                "nuclear": 12,
                "oil": 650,
                "solar": 45,
                "unknown": 700,
                "wind": 11
            },
            "productionCo2IntensitySources": {
                "biomass": "IPCC 2014",
                "coal": "IPCC 2014",
                "gas": "IPCC 2014",
                "geothermal": "IPCC 2014",
                "hydro": "IPCC 2014",
                "nuclear": "IPCC 2014",
                "oil": "UK POST 2014",
                "solar": "IPCC 2014",
                "unknown": "assumes thermal (coal, gas, oil or biomass)",
                "wind": "IPCC 2014"
            },
            "renewableRatio": 0.4803,
            "renewableRatioProduction": 0.36469999999999997,
            "source": "entsoe.eu",
            "stateDatetime": "2022-07-08T22:00:00Z",
            "storage": {
                "battery": null,
                "hydro": -0.0
            },
            "totalCo2Discharge": 0.0,
            "totalCo2Export": 63129450.00000001,
            "totalCo2Import": 116958730.0,
            "totalCo2NetExchange": 53829279.99999999,
            "totalCo2Production": 32438000.0,
            "totalCo2Storage": 0,
            "totalConsumption": 1108.75,
            "totalDischarge": 0,
            "totalExport": 813.0,
            "totalImport": 838.75,
            "totalProduction": 1083.0,
            "totalStorage": 0
        },
        {
            "_isFinestGranularity": true,
            "capacity": {
                "battery storage": 0.0,
                "biomass": 58.0,
                "coal": 967.0,
                "gas": 548.0,
                "geothermal": 0.0,
                "hydro": 1121.0,
                "hydro storage": 180.0,
                "nuclear": 696.0,
                "oil": 0.0,
                "solar": 289.0,
                "unknown": null,
                "wind": 3.0
            },
            "co2intensity": 98.01,
            "co2intensityProduction": 31.08,
            "countryCode": "SI",
            "dischargeCo2Intensities": {
                "battery": 227.82342464167832,
                "hydro": 227.82342464167832
            },
            "dischargeCo2IntensitySources": {
                "battery": "electricityMap, 2021 average",
                "hydro": "electricityMap, 2021 average"
            },
            "estimationMethod": null,
            "exchange": {
                "AT": 227.5,
                "HR": 591.0,
                "IT-NO": -804.0
            },
            "exchangeCapacities": {},
            "exchangeCo2Intensities": {
                "AT": 81.41,
                "HR": 215.09,
                "IT-NO": 98.2
            },
            "fossilFuelRatio": 0.1881,
            "fossilFuelRatioProduction": 0.0246,
            "maxCapacity": 1121.0,
            "maxDischarge": 0,
            "maxExport": 804.0,
            "maxExportCapacity": null,
            "maxImport": 591.0,
            "maxImportCapacity": null,
            "maxProduction": 666.0,
            "maxStorage": 0,
            "maxStorageCapacity": 180.0,
            "price": {
                "currency": "EUR",
                "value": 284.05
            },
            "production": {
                "biomass": 18.0,
                "coal": 0.0,
                "gas": 24.0,
                "geothermal": null,
                "hydro": 267.0,
                "nuclear": 666.0,
                "oil": 0.0,
                "solar": 0.0,
                "unknown": null,
                "wind": 0.0
            },
            "productionCo2Intensities": {
                "biomass": 230,
                "coal": 820,
                "gas": 490,
                "geothermal": 38,
                "hydro": 24,
                "nuclear": 12,
                "oil": 650,
                "solar": 45,
                "unknown": 700,
                "wind": 11
            },
            "productionCo2IntensitySources": {
                "biomass": "IPCC 2014",
                "coal": "IPCC 2014",
                "gas": "IPCC 2014",
                "geothermal": "IPCC 2014",
                "hydro": "IPCC 2014",
                "nuclear": "IPCC 2014",
                "oil": "UK POST 2014",
                "solar": "IPCC 2014",
                "unknown": "assumes thermal (coal, gas, oil or biomass)",
                "wind": "IPCC 2014"
            },
            "renewableRatio": 0.3924,
            "renewableRatioProduction": 0.2923,
            "source": "entsoe.eu",
            "stateDatetime": "2022-07-08T23:00:00Z",
            "storage": {
                "battery": null,
                "hydro": -0.0
            },
            "totalCo2Discharge": 0.0,
            "totalCo2Export": 78952800.0,
            "totalCo2Import": 145638965.0,
            "totalCo2NetExchange": 66686165.0,
            "totalCo2Production": 30300000.0,
            "totalCo2Storage": 0,
            "totalConsumption": 989.5,
            "totalDischarge": 0,
            "totalExport": 804.0,
            "totalImport": 818.5,
            "totalProduction": 975.0,
            "totalStorage": 0
        },
        {
            "_isFinestGranularity": true,
            "capacity": {
                "battery storage": 0.0,
                "biomass": 58.0,
                "coal": 967.0,
                "gas": 548.0,
                "geothermal": 0.0,
                "hydro": 1121.0,
                "hydro storage": 180.0,
                "nuclear": 696.0,
                "oil": 0.0,
                "solar": 289.0,
                "unknown": null,
                "wind": 3.0
            },
            "co2intensity": 120.53,
            "co2intensityProduction": 31.53,
            "countryCode": "SI",
            "dischargeCo2Intensities": {
                "battery": 227.82342464167832,
                "hydro": 227.82342464167832
            },
            "dischargeCo2IntensitySources": {
                "battery": "electricityMap, 2021 average",
                "hydro": "electricityMap, 2021 average"
            },
            "estimationMethod": null,
            "exchange": {
                "AT": 139.25,
                "HR": 779.0,
                "IT-NO": -757.0
            },
            "exchangeCapacities": {},
            "exchangeCo2Intensities": {
                "AT": 80.83,
                "HR": 232.42,
                "IT-NO": 120.68
            },
            "fossilFuelRatio": 0.2335,
            "fossilFuelRatioProduction": 0.0262,
            "maxCapacity": 1121.0,
            "maxDischarge": 0,
            "maxExport": 757.0,
            "maxExportCapacity": null,
            "maxImport": 779.0,
            "maxImportCapacity": null,
            "maxProduction": 666.0,
            "maxStorage": 0,
            "maxStorageCapacity": 180.0,
            "price": {
                "currency": "EUR",
                "value": 216.28
            },
            "production": {
                "biomass": 18.0,
                "coal": 0.0,
                "gas": 24.0,
                "geothermal": null,
                "hydro": 208.0,
                "nuclear": 666.0,
                "oil": 0.0,
                "solar": 0.0,
                "unknown": null,
                "wind": 0.0
            },
            "productionCo2Intensities": {
                "biomass": 230,
                "coal": 820,
                "gas": 490,
                "geothermal": 38,
                "hydro": 24,
                "nuclear": 12,
                "oil": 650,
                "solar": 45,
                "unknown": 700,
                "wind": 11
            },
            "productionCo2IntensitySources": {
                "biomass": "IPCC 2014",
                "coal": "IPCC 2014",
                "gas": "IPCC 2014",
                "geothermal": "IPCC 2014",
                "hydro": "IPCC 2014",
                "nuclear": "IPCC 2014",
                "oil": "UK POST 2014",
                "solar": "IPCC 2014",
                "unknown": "assumes thermal (coal, gas, oil or biomass)",
                "wind": "IPCC 2014"
            },
            "renewableRatio": 0.3481,
            "renewableRatioProduction": 0.24670000000000003,
            "source": "entsoe.eu",
            "stateDatetime": "2022-07-09T00:00:00Z",
            "storage": {
                "battery": null,
                "hydro": -0.0
            },
            "totalCo2Discharge": 0.0,
            "totalCo2Export": 91354760.0,
            "totalCo2Import": 192310757.5,
            "totalCo2NetExchange": 100955997.5,
            "totalCo2Production": 28884000.0,
            "totalCo2Storage": 0,
            "totalConsumption": 1077.25,
            "totalDischarge": 0,
            "totalExport": 757.0,
            "totalImport": 918.25,
            "totalProduction": 916.0,
            "totalStorage": 0
        },
        {
            "_isFinestGranularity": true,
            "capacity": {
                "battery storage": 0.0,
                "biomass": 58.0,
                "coal": 967.0,
                "gas": 548.0,
                "geothermal": 0.0,
                "hydro": 1121.0,
                "hydro storage": 180.0,
                "nuclear": 696.0,
                "oil": 0.0,
                "solar": 289.0,
                "unknown": null,
                "wind": 3.0
            },
            "co2intensity": 110.86,
            "co2intensityProduction": 31.49,
            "countryCode": "SI",
            "dischargeCo2Intensities": {
                "battery": 227.82342464167832,
                "hydro": 227.82342464167832
            },
            "dischargeCo2IntensitySources": {
                "battery": "electricityMap, 2021 average",
                "hydro": "electricityMap, 2021 average"
            },
            "estimationMethod": null,
            "exchange": {
                "AT": 210.75,
                "HR": 722.0,
                "IT-NO": -990.0
            },
            "exchangeCapacities": {},
            "exchangeCo2Intensities": {
                "AT": 91.46,
                "HR": 217.77,
                "IT-NO": 110.86
            },
            "fossilFuelRatio": 0.2182,
            "fossilFuelRatioProduction": 0.026099999999999998,
            "maxCapacity": 1121.0,
            "maxDischarge": 0,
            "maxExport": 990.0,
            "maxExportCapacity": null,
            "maxImport": 722.0,
            "maxImportCapacity": null,
            "maxProduction": 666.0,
            "maxStorage": 0,
            "maxStorageCapacity": 180.0,
            "price": {
                "currency": "EUR",
                "value": 206.48
            },
            "production": {
                "biomass": 18.0,
                "coal": 0.0,
                "gas": 24.0,
                "geothermal": null,
                "hydro": 213.0,
                "nuclear": 666.0,
                "oil": 0.0,
                "solar": 0.0,
                "unknown": null,
                "wind": 0.0
            },
            "productionCo2Intensities": {
                "biomass": 230,
                "coal": 820,
                "gas": 490,
                "geothermal": 38,
                "hydro": 24,
                "nuclear": 12,
                "oil": 650,
                "solar": 45,
                "unknown": 700,
                "wind": 11
            },
            "productionCo2IntensitySources": {
                "biomass": "IPCC 2014",
                "coal": "IPCC 2014",
                "gas": "IPCC 2014",
                "geothermal": "IPCC 2014",
                "hydro": "IPCC 2014",
                "nuclear": "IPCC 2014",
                "oil": "UK POST 2014",
                "solar": "IPCC 2014",
                "unknown": "assumes thermal (coal, gas, oil or biomass)",
                "wind": "IPCC 2014"
            },
            "renewableRatio": 0.3601,
            "renewableRatioProduction": 0.25079999999999997,
            "source": "entsoe.eu",
            "stateDatetime": "2022-07-09T01:00:00Z",
            "storage": {
                "battery": null,
                "hydro": -0.0
            },
            "totalCo2Discharge": 0.0,
            "totalCo2Export": 109751400.0,
            "totalCo2Import": 176505135.0,
            "totalCo2NetExchange": 66753735.0,
            "totalCo2Production": 29004000.0,
            "totalCo2Storage": 0,
            "totalConsumption": 863.75,
            "totalDischarge": 0,
            "totalExport": 990.0,
            "totalImport": 932.75,
            "totalProduction": 921.0,
            "totalStorage": 0
        },
        {
            "_isFinestGranularity": true,
            "capacity": {
                "battery storage": 0.0,
                "biomass": 58.0,
                "coal": 967.0,
                "gas": 548.0,
                "geothermal": 0.0,
                "hydro": 1121.0,
                "hydro storage": 180.0,
                "nuclear": 696.0,
                "oil": 0.0,
                "solar": 289.0,
                "unknown": null,
                "wind": 3.0
            },
            "co2intensity": 111.4,
            "co2intensityProduction": 31.54,
            "countryCode": "SI",
            "dischargeCo2Intensities": {
                "battery": 227.82342464167832,
                "hydro": 227.82342464167832
            },
            "dischargeCo2IntensitySources": {
                "battery": "electricityMap, 2021 average",
                "hydro": "electricityMap, 2021 average"
            },
            "estimationMethod": null,
            "exchange": {
                "AT": 87.25,
                "HR": 715.0,
                "IT-NO": -473.0
            },
            "exchangeCapacities": {},
            "exchangeCo2Intensities": {
                "AT": 96.49,
                "HR": 215.45,
                "IT-NO": 111.45
            },
            "fossilFuelRatio": 0.23010000000000003,
            "fossilFuelRatioProduction": 0.0262,
            "maxCapacity": 1121.0,
            "maxDischarge": 0,
            "maxExport": 473.0,
            "maxExportCapacity": null,
            "maxImport": 715.0,
            "maxImportCapacity": null,
            "maxProduction": 666.0,
            "maxStorage": 0,
            "maxStorageCapacity": 180.0,
            "price": {
                "currency": "EUR",
                "value": 197.51
            },
            "production": {
                "biomass": 18.0,
                "coal": 0.0,
                "gas": 24.0,
                "geothermal": null,
                "hydro": 207.0,
                "nuclear": 666.0,
                "oil": 0.0,
                "solar": 0.0,
                "unknown": null,
                "wind": 0.0
            },
            "productionCo2Intensities": {
                "biomass": 230,
                "coal": 820,
                "gas": 490,
                "geothermal": 38,
                "hydro": 24,
                "nuclear": 12,
                "oil": 650,
                "solar": 45,
                "unknown": 700,
                "wind": 11
            },
            "productionCo2IntensitySources": {
                "biomass": "IPCC 2014",
                "coal": "IPCC 2014",
                "gas": "IPCC 2014",
                "geothermal": "IPCC 2014",
                "hydro": "IPCC 2014",
                "nuclear": "IPCC 2014",
                "oil": "UK POST 2014",
                "solar": "IPCC 2014",
                "unknown": "assumes thermal (coal, gas, oil or biomass)",
                "wind": "IPCC 2014"
            },
            "renewableRatio": 0.3185,
            "renewableRatioProduction": 0.2459,
            "source": "entsoe.eu",
            "stateDatetime": "2022-07-09T02:00:00Z",
            "storage": {
                "battery": null,
                "hydro": -0.0
            },
            "totalCo2Discharge": 0.0,
            "totalCo2Export": 52715850.0,
            "totalCo2Import": 162465502.5,
            "totalCo2NetExchange": 109749652.5,
            "totalCo2Production": 28860000.0,
            "totalCo2Storage": 0,
            "totalConsumption": 1244.25,
            "totalDischarge": 0,
            "totalExport": 473.0,
            "totalImport": 802.25,
            "totalProduction": 915.0,
            "totalStorage": 0
        },
        {
            "_isFinestGranularity": true,
            "capacity": {
                "battery storage": 0.0,
                "biomass": 58.0,
                "coal": 967.0,
                "gas": 548.0,
                "geothermal": 0.0,
                "hydro": 1121.0,
                "hydro storage": 180.0,
                "nuclear": 696.0,
                "oil": 0.0,
                "solar": 289.0,
                "unknown": null,
                "wind": 3.0
            },
            "co2intensity": 116.66,
            "co2intensityProduction": 33.53,
            "countryCode": "SI",
            "dischargeCo2Intensities": {
                "battery": 227.82342464167832,
                "hydro": 227.82342464167832
            },
            "dischargeCo2IntensitySources": {
                "battery": "electricityMap, 2021 average",
                "hydro": "electricityMap, 2021 average"
            },
            "estimationMethod": null,
            "exchange": {
                "AT": 97.75,
                "HR": 750.0,
                "IT-NO": -677.0
            },
            "exchangeCapacities": {},
            "exchangeCo2Intensities": {
                "AT": 98.5,
                "HR": 221.16,
                "IT-NO": 116.71
            },
            "fossilFuelRatio": 0.2419,
            "fossilFuelRatioProduction": 0.0304,
            "maxCapacity": 1121.0,
            "maxDischarge": 0,
            "maxExport": 677.0,
            "maxExportCapacity": null,
            "maxImport": 750.0,
            "maxImportCapacity": null,
            "maxProduction": 667.0,
            "maxStorage": 0,
            "maxStorageCapacity": 180.0,
            "price": {
                "currency": "EUR",
                "value": 206.95
            },
            "production": {
                "biomass": 18.0,
                "coal": 0.0,
                "gas": 28.0,
                "geothermal": null,
                "hydro": 207.0,
                "nuclear": 667.0,
                "oil": 0.0,
                "solar": 1.0,
                "unknown": null,
                "wind": 0.0
            },
            "productionCo2Intensities": {
                "biomass": 230,
                "coal": 820,
                "gas": 490,
                "geothermal": 38,
                "hydro": 24,
                "nuclear": 12,
                "oil": 650,
                "solar": 45,
                "unknown": 700,
                "wind": 11
            },
            "productionCo2IntensitySources": {
                "biomass": "IPCC 2014",
                "coal": "IPCC 2014",
                "gas": "IPCC 2014",
                "geothermal": "IPCC 2014",
                "hydro": "IPCC 2014",
                "nuclear": "IPCC 2014",
                "oil": "UK POST 2014",
                "solar": "IPCC 2014",
                "unknown": "assumes thermal (coal, gas, oil or biomass)",
                "wind": "IPCC 2014"
            },
            "renewableRatio": 0.32020000000000004,
            "renewableRatioProduction": 0.24539999999999998,
            "source": "entsoe.eu",
            "stateDatetime": "2022-07-09T03:00:00Z",
            "storage": {
                "battery": null,
                "hydro": -0.0
            },
            "totalCo2Discharge": 0.0,
            "totalCo2Export": 79012670.0,
            "totalCo2Import": 175498375.0,
            "totalCo2NetExchange": 96485705.0,
            "totalCo2Production": 30877000.0,
            "totalCo2Storage": 0,
            "totalConsumption": 1091.75,
            "totalDischarge": 0,
            "totalExport": 677.0,
            "totalImport": 847.75,
            "totalProduction": 921.0,
            "totalStorage": 0
        },
        {
            "_isFinestGranularity": true,
            "capacity": {
                "battery storage": 0.0,
                "biomass": 58.0,
                "coal": 967.0,
                "gas": 548.0,
                "geothermal": 0.0,
                "hydro": 1121.0,
                "hydro storage": 180.0,
                "nuclear": 696.0,
                "oil": 0.0,
                "solar": 289.0,
                "unknown": null,
                "wind": 3.0
            },
            "co2intensity": 101.26,
            "co2intensityProduction": 31.42,
            "countryCode": "SI",
            "dischargeCo2Intensities": {
                "battery": 227.82342464167832,
                "hydro": 227.82342464167832
            },
            "dischargeCo2IntensitySources": {
                "battery": "electricityMap, 2021 average",
                "hydro": "electricityMap, 2021 average"
            },
            "estimationMethod": null,
            "exchange": {
                "AT": 178.25,
                "HR": 612.0,
                "IT-NO": -747.0
            },
            "exchangeCapacities": {},
            "exchangeCo2Intensities": {
                "AT": 95.63,
                "HR": 211.86,
                "IT-NO": 101.33
            },
            "fossilFuelRatio": 0.2032,
            "fossilFuelRatioProduction": 0.0252,
            "maxCapacity": 1121.0,
            "maxDischarge": 0,
            "maxExport": 747.0,
            "maxExportCapacity": null,
            "maxImport": 612.0,
            "maxImportCapacity": null,
            "maxProduction": 667.0,
            "maxStorage": 0,
            "maxStorageCapacity": 180.0,
            "price": {
                "currency": "EUR",
                "value": 241.96
            },
            "production": {
                "biomass": 18.0,
                "coal": 0.0,
                "gas": 24.0,
                "geothermal": null,
                "hydro": 236.0,
                "nuclear": 667.0,
                "oil": 0.0,
                "solar": 9.0,
                "unknown": null,
                "wind": 0.0
            },
            "productionCo2Intensities": {
                "biomass": 230,
                "coal": 820,
                "gas": 490,
                "geothermal": 38,
                "hydro": 24,
                "nuclear": 12,
                "oil": 650,
                "solar": 45,
                "unknown": 700,
                "wind": 11
            },
            "productionCo2IntensitySources": {
                "biomass": "IPCC 2014",
                "coal": "IPCC 2014",
                "gas": "IPCC 2014",
                "geothermal": "IPCC 2014",
                "hydro": "IPCC 2014",
                "nuclear": "IPCC 2014",
                "oil": "UK POST 2014",
                "solar": "IPCC 2014",
                "unknown": "assumes thermal (coal, gas, oil or biomass)",
                "wind": "IPCC 2014"
            },
            "renewableRatio": 0.3608,
            "renewableRatioProduction": 0.2757,
            "source": "entsoe.eu",
            "stateDatetime": "2022-07-09T04:00:00Z",
            "storage": {
                "battery": null,
                "hydro": -0.0
            },
            "totalCo2Discharge": 0.0,
            "totalCo2Export": 75693510.0,
            "totalCo2Import": 146704367.5,
            "totalCo2NetExchange": 71010857.5,
            "totalCo2Production": 29973000.0,
            "totalCo2Storage": 0,
            "totalConsumption": 997.25,
            "totalDischarge": 0,
            "totalExport": 747.0,
            "totalImport": 790.25,
            "totalProduction": 954.0,
            "totalStorage": 0
        },
        {
            "_isFinestGranularity": true,
            "capacity": {
                "battery storage": 0.0,
                "biomass": 58.0,
                "coal": 967.0,
                "gas": 548.0,
                "geothermal": 0.0,
                "hydro": 1121.0,
                "hydro storage": 180.0,
                "nuclear": 696.0,
                "oil": 0.0,
                "solar": 289.0,
                "unknown": null,
                "wind": 3.0
            },
            "co2intensity": 73.2,
            "co2intensityProduction": 30.34,
            "countryCode": "SI",
            "dischargeCo2Intensities": {
                "battery": 227.82342464167832,
                "hydro": 227.82342464167832
            },
            "dischargeCo2IntensitySources": {
                "battery": "electricityMap, 2021 average",
                "hydro": "electricityMap, 2021 average"
            },
            "estimationMethod": null,
            "exchange": {
                "AT": 24.25,
                "HR": 454.0,
                "IT-NO": -219.0
            },
            "exchangeCapacities": {},
            "exchangeCo2Intensities": {
                "AT": 101.15,
                "HR": 183.46,
                "IT-NO": 73.18
            },
            "fossilFuelRatio": 0.1564,
            "fossilFuelRatioProduction": 0.0203,
            "maxCapacity": 1121.0,
            "maxDischarge": 0,
            "maxExport": 219.0,
            "maxExportCapacity": null,
            "maxImport": 454.0,
            "maxImportCapacity": null,
            "maxProduction": 666.0,
            "maxStorage": 0,
            "maxStorageCapacity": 180.0,
            "price": {
                "currency": "EUR",
                "value": 238.75
            },
            "production": {
                "biomass": 18.0,
                "coal": 0.0,
                "gas": 24.0,
                "geothermal": null,
                "hydro": 447.0,
                "nuclear": 666.0,
                "oil": 0.0,
                "solar": 29.0,
                "unknown": null,
                "wind": 0.0
            },
            "productionCo2Intensities": {
                "biomass": 230,
                "coal": 820,
                "gas": 490,
                "geothermal": 38,
                "hydro": 24,
                "nuclear": 12,
                "oil": 650,
                "solar": 45,
                "unknown": 700,
                "wind": 11
            },
            "productionCo2IntensitySources": {
                "biomass": "IPCC 2014",
                "coal": "IPCC 2014",
                "gas": "IPCC 2014",
                "geothermal": "IPCC 2014",
                "hydro": "IPCC 2014",
                "nuclear": "IPCC 2014",
                "oil": "UK POST 2014",
                "solar": "IPCC 2014",
                "unknown": "assumes thermal (coal, gas, oil or biomass)",
                "wind": "IPCC 2014"
            },
            "renewableRatio": 0.40509999999999996,
            "renewableRatioProduction": 0.4172,
            "source": "entsoe.eu",
            "stateDatetime": "2022-07-09T05:00:00Z",
            "storage": {
                "battery": null,
                "hydro": -0.0
            },
            "totalCo2Discharge": 0.0,
            "totalCo2Export": 16026420.000000002,
            "totalCo2Import": 85743727.5,
            "totalCo2NetExchange": 69717307.5,
            "totalCo2Production": 35925000.0,
            "totalCo2Storage": 0,
            "totalConsumption": 1443.25,
            "totalDischarge": 0,
            "totalExport": 219.0,
            "totalImport": 478.25,
            "totalProduction": 1184.0,
            "totalStorage": 0
        },
        {
            "_isFinestGranularity": true,
            "capacity": {
                "battery storage": 0.0,
                "biomass": 58.0,
                "coal": 967.0,
                "gas": 548.0,
                "geothermal": 0.0,
                "hydro": 1121.0,
                "hydro storage": 180.0,
                "nuclear": 696.0,
                "oil": 0.0,
                "solar": 289.0,
                "unknown": null,
                "wind": 3.0
            },
            "co2intensity": 78.82,
            "co2intensityProduction": 30.67,
            "countryCode": "SI",
            "dischargeCo2Intensities": {
                "battery": 227.82342464167832,
                "hydro": 227.82342464167832
            },
            "dischargeCo2IntensitySources": {
                "battery": "electricityMap, 2021 average",
                "hydro": "electricityMap, 2021 average"
            },
            "estimationMethod": null,
            "exchange": {
                "AT": 339.75,
                "HR": 388.0,
                "IT-NO": -1074.0
            },
            "exchangeCapacities": {},
            "exchangeCo2Intensities": {
                "AT": 89.76,
                "HR": 166.63,
                "IT-NO": 78.82
            },
            "fossilFuelRatio": 0.12269999999999999,
            "fossilFuelRatioProduction": 0.0181,
            "maxCapacity": 1121.0,
            "maxDischarge": 118.0,
            "maxExport": 1074.0,
            "maxExportCapacity": null,
            "maxImport": 388.0,
            "maxImportCapacity": null,
            "maxProduction": 666.0,
            "maxStorage": 0,
            "maxStorageCapacity": 180.0,
            "price": {
                "currency": "EUR",
                "value": 241.41
            },
            "production": {
                "biomass": 18.0,
                "coal": 0.0,
                "gas": 23.0,
                "geothermal": null,
                "hydro": 384.0,
                "nuclear": 666.0,
                "oil": 0.0,
                "solar": 59.0,
                "unknown": null,
                "wind": 0.0
            },
            "productionCo2Intensities": {
                "biomass": 230,
                "coal": 820,
                "gas": 490,
                "geothermal": 38,
                "hydro": 24,
                "nuclear": 12,
                "oil": 650,
                "solar": 45,
                "unknown": 700,
                "wind": 11
            },
            "productionCo2IntensitySources": {
                "biomass": "IPCC 2014",
                "coal": "IPCC 2014",
                "gas": "IPCC 2014",
                "geothermal": "IPCC 2014",
                "hydro": "IPCC 2014",
                "nuclear": "IPCC 2014",
                "oil": "UK POST 2014",
                "solar": "IPCC 2014",
                "unknown": "assumes thermal (coal, gas, oil or biomass)",
                "wind": "IPCC 2014"
            },
            "renewableRatio": 0.5065999999999999,
            "renewableRatioProduction": 0.45659999999999995,
            "source": "entsoe.eu",
            "stateDatetime": "2022-07-09T06:00:00Z",
            "storage": {
                "battery": null,
                "hydro": -118.0
            },
            "totalCo2Discharge": 26883164.107718043,
            "totalCo2Export": 84652680.0,
            "totalCo2Import": 95148400.0,
            "totalCo2NetExchange": 10495720.0,
            "totalCo2Production": 35273000.0,
            "totalCo2Storage": 0,
            "totalConsumption": 921.75,
            "totalDischarge": 118.0,
            "totalExport": 1074.0,
            "totalImport": 727.75,
            "totalProduction": 1150.0,
            "totalStorage": 0
        },
        {
            "_isFinestGranularity": true,
            "capacity": {
                "battery storage": 0.0,
                "biomass": 58.0,
                "coal": 967.0,
                "gas": 548.0,
                "geothermal": 0.0,
                "hydro": 1121.0,
                "hydro storage": 180.0,
                "nuclear": 696.0,
                "oil": 0.0,
                "solar": 289.0,
                "unknown": null,
                "wind": 3.0
            },
            "co2intensity": 68.67,
            "co2intensityProduction": 32.26,
            "countryCode": "SI",
            "dischargeCo2Intensities": {
                "battery": 227.82342464167832,
                "hydro": 227.82342464167832
            },
            "dischargeCo2IntensitySources": {
                "battery": "electricityMap, 2021 average",
                "hydro": "electricityMap, 2021 average"
            },
            "estimationMethod": null,
            "exchange": {
                "AT": 513.0,
                "HR": 265.0,
                "IT-NO": -928.0
            },
            "exchangeCapacities": {},
            "exchangeCo2Intensities": {
                "AT": 99.66,
                "HR": 147.48,
                "IT-NO": 68.6
            },
            "fossilFuelRatio": 0.109,
            "fossilFuelRatioProduction": 0.0227,
            "maxCapacity": 1121.0,
            "maxDischarge": 0,
            "maxExport": 928.0,
            "maxExportCapacity": null,
            "maxImport": 513.0,
            "maxImportCapacity": null,
            "maxProduction": 665.0,
            "maxStorage": 0,
            "maxStorageCapacity": 180.0,
            "price": {
                "currency": "EUR",
                "value": 195.57
            },
            "production": {
                "biomass": 18.0,
                "coal": 0.0,
                "gas": 23.0,
                "geothermal": null,
                "hydro": 215.0,
                "nuclear": 665.0,
                "oil": 0.0,
                "solar": 91.0,
                "unknown": null,
                "wind": 0.0
            },
            "productionCo2Intensities": {
                "biomass": 230,
                "coal": 820,
                "gas": 490,
                "geothermal": 38,
                "hydro": 24,
                "nuclear": 12,
                "oil": 650,
                "solar": 45,
                "unknown": 700,
                "wind": 11
            },
            "productionCo2IntensitySources": {
                "biomass": "IPCC 2014",
                "coal": "IPCC 2014",
                "gas": "IPCC 2014",
                "geothermal": "IPCC 2014",
                "hydro": "IPCC 2014",
                "nuclear": "IPCC 2014",
                "oil": "UK POST 2014",
                "solar": "IPCC 2014",
                "unknown": "assumes thermal (coal, gas, oil or biomass)",
                "wind": "IPCC 2014"
            },
            "renewableRatio": 0.4792,
            "renewableRatioProduction": 0.32020000000000004,
            "source": "entsoe.eu",
            "stateDatetime": "2022-07-09T07:00:00Z",
            "storage": {
                "battery": null,
                "hydro": -0.0
            },
            "totalCo2Discharge": 0.0,
            "totalCo2Export": 63660799.99999999,
            "totalCo2Import": 90207780.0,
            "totalCo2NetExchange": 26546980.000000007,
            "totalCo2Production": 32645000.0,
            "totalCo2Storage": 0,
            "totalConsumption": 862.0,
            "totalDischarge": 0,
            "totalExport": 928.0,
            "totalImport": 778.0,
            "totalProduction": 1012.0,
            "totalStorage": 0
        },
        {
            "_isFinestGranularity": true,
            "capacity": {
                "battery storage": 0.0,
                "biomass": 58.0,
                "coal": 967.0,
                "gas": 548.0,
                "geothermal": 0.0,
                "hydro": 1121.0,
                "hydro storage": 180.0,
                "nuclear": 696.0,
                "oil": 0.0,
                "solar": 289.0,
                "unknown": null,
                "wind": 3.0
            },
            "co2intensity": 63.63,
            "co2intensityProduction": 34.56,
            "countryCode": "SI",
            "dischargeCo2Intensities": {
                "battery": 227.82342464167832,
                "hydro": 227.82342464167832
            },
            "dischargeCo2IntensitySources": {
                "battery": "electricityMap, 2021 average",
                "hydro": "electricityMap, 2021 average"
            },
            "estimationMethod": null,
            "exchange": {
                "AT": 659.25,
                "HR": 199.0,
                "IT-NO": -1003.0
            },
            "exchangeCapacities": {},
            "exchangeCo2Intensities": {
                "AT": 83.97,
                "HR": 144.52,
                "IT-NO": 63.63
            },
            "fossilFuelRatio": 0.0898,
            "fossilFuelRatioProduction": 0.026600000000000002,
            "maxCapacity": 1121.0,
            "maxDischarge": 0,
            "maxExport": 1003.0,
            "maxExportCapacity": null,
            "maxImport": 659.25,
            "maxImportCapacity": null,
            "maxProduction": 665.0,
            "maxStorage": 0,
            "maxStorageCapacity": 180.0,
            "price": {
                "currency": "EUR",
                "value": 162.45
            },
            "production": {
                "biomass": 19.0,
                "coal": 0.0,
                "gas": 27.0,
                "geothermal": null,
                "hydro": 199.0,
                "nuclear": 665.0,
                "oil": 0.0,
                "solar": 105.0,
                "unknown": null,
                "wind": 0.0
            },
            "productionCo2Intensities": {
                "biomass": 230,
                "coal": 820,
                "gas": 490,
                "geothermal": 38,
                "hydro": 24,
                "nuclear": 12,
                "oil": 650,
                "solar": 45,
                "unknown": 700,
                "wind": 11
            },
            "productionCo2IntensitySources": {
                "biomass": "IPCC 2014",
                "coal": "IPCC 2014",
                "gas": "IPCC 2014",
                "geothermal": "IPCC 2014",
                "hydro": "IPCC 2014",
                "nuclear": "IPCC 2014",
                "oil": "UK POST 2014",
                "solar": "IPCC 2014",
                "unknown": "assumes thermal (coal, gas, oil or biomass)",
                "wind": "IPCC 2014"
            },
            "renewableRatio": 0.5196999999999999,
            "renewableRatioProduction": 0.3182,
            "source": "entsoe.eu",
            "stateDatetime": "2022-07-09T08:00:00Z",
            "storage": {
                "battery": null,
                "hydro": -0.0
            },
            "totalCo2Discharge": 0.0,
            "totalCo2Export": 63820890.0,
            "totalCo2Import": 84116702.5,
            "totalCo2NetExchange": 20295812.5,
            "totalCo2Production": 35081000.0,
            "totalCo2Storage": 0,
            "totalConsumption": 870.25,
            "totalDischarge": 0,
            "totalExport": 1003.0,
            "totalImport": 858.25,
            "totalProduction": 1015.0,
            "totalStorage": 0
        },
        {
            "_isFinestGranularity": true,
            "capacity": {
                "battery storage": 0.0,
                "biomass": 58.0,
                "coal": 967.0,
                "gas": 548.0,
                "geothermal": 0.0,
                "hydro": 1121.0,
                "hydro storage": 180.0,
                "nuclear": 696.0,
                "oil": 0.0,
                "solar": 289.0,
                "unknown": null,
                "wind": 3.0
            },
            "co2intensity": 164.7,
            "co2intensityProduction": 212.81,
            "countryCode": "SI",
            "dischargeCo2Intensities": {
                "battery": 227.82342464167832,
                "hydro": 227.82342464167832
            },
            "dischargeCo2IntensitySources": {
                "battery": "electricityMap, 2021 average",
                "hydro": "electricityMap, 2021 average"
            },
            "estimationMethod": "ESTIMATED_TIME_SLICER_AVERAGE",
            "exchange": {
                "AT": 801.75,
                "HR": 178.0,
                "IT-NO": -914.0
            },
            "exchangeCapacities": {},
            "exchangeCo2Intensities": {
                "AT": 82.24,
                "HR": 144.95,
                "IT-NO": 164.71
            },
            "fossilFuelRatio": 0.2007,
            "fossilFuelRatioProduction": 0.2403,
            "maxCapacity": 1121.0,
            "maxDischarge": 34.62,
            "maxExport": 914.0,
            "maxExportCapacity": null,
            "maxImport": 801.75,
            "maxImportCapacity": null,
            "maxProduction": 658.75,
            "maxStorage": 0,
            "maxStorageCapacity": 180.0,
            "price": {
                "currency": "EUR",
                "value": 141.46
            },
            "production": {
                "biomass": 18.88,
                "coal": 319.62,
                "gas": 25.0,
                "geothermal": null,
                "hydro": 270.38,
                "nuclear": 658.75,
                "oil": 0.69,
                "solar": 107.75,
                "unknown": null,
                "wind": 1.05
            },
            "productionCo2Intensities": {
                "biomass": 230,
                "coal": 820,
                "gas": 490,
                "geothermal": 38,
                "hydro": 24,
                "nuclear": 12,
                "oil": 650,
                "solar": 45,
                "unknown": 700,
                "wind": 11
            },
            "productionCo2IntensitySources": {
                "biomass": "IPCC 2014",
                "coal": "IPCC 2014",
                "gas": "IPCC 2014",
                "geothermal": "IPCC 2014",
                "hydro": "IPCC 2014",
                "nuclear": "IPCC 2014",
                "oil": "UK POST 2014",
                "solar": "IPCC 2014",
                "unknown": "assumes thermal (coal, gas, oil or biomass)",
                "wind": "IPCC 2014"
            },
            "renewableRatio": 0.4982,
            "renewableRatioProduction": 0.3012,
            "source": "electricityMap Estimation",
            "stateDatetime": "2022-07-09T09:00:00Z",
            "storage": {
                "battery": null,
                "hydro": -34.62
            },
            "totalCo2Discharge": 7887246.961094903,
            "totalCo2Export": 150544940.0,
            "totalCo2Import": 91737019.99999999,
            "totalCo2NetExchange": -58807920.000000015,
            "totalCo2Production": 298383720.0,
            "totalCo2Storage": 0,
            "totalConsumption": 1502.5,
            "totalDischarge": 34.62,
            "totalExport": 914.0,
            "totalImport": 979.75,
            "totalProduction": 1402.12,
            "totalStorage": 0
        }
    ]
}