{
    "data": [
        {
            "_isFinestGranularity": true,
            "capacity": {
                "battery storage": 0.0,
                "biomass": 663.4,
                "coal": 2420.0,
                "gas": 9135.2,
                "geothermal": 0.0,
                "hydro": 1014.2,
                "hydro storage": 0.0,
                "nuclear": 0.0,
                "oil": 66.0,
                "solar": 4008.3,
                "unknown": 0.0,
                "wind": 5499.5
            },
            "co2intensity": 321.76,
            "co2intensityProduction": 323.47,
            "countryCode": "IT-SO",
            "dischargeCo2Intensities": {
                "battery": 341.85417092564336,
                "hydro": 341.85417092564336
            },
            "dischargeCo2IntensitySources": {
                "battery": "electricityMap, 2021 average",
                "hydro": "electricityMap, 2021 average"
            },
            "estimationMethod": 0.0,
            "exchange": {
                "GR": 495.0,
                "IT-CSO": -4708.0,
                "IT-SIC": -109.0
            },
            "exchangeCapacities": {
                "GR": [
                    -500.0,
                    500.0
                ]
            },
            "exchangeCo2Intensities": {
                "GR": 295.2,
                "IT-CSO": 321.76,
                "IT-SIC": 321.76
            },
            "fossilFuelRatio": 0.5202,
            "fossilFuelRatioProduction": 0.5222,
            "maxCapacity": 9135.2,
            "maxDischarge": 0,
            "maxExport": 4708.0,
            "maxExportCapacity": 500.0,
            "maxImport": 495.0,
            "maxImportCapacity": 500.0,
            "maxProduction": 2978.0,
            "maxStorage": 0,
            "maxStorageCapacity": 0.0,
            "price": {
                "currency": "EUR",
                "value": 409.69
            },
            "production": {
                "biomass": 307.0,
                "coal": 892.0,
                "gas": 2978.0,
                "geothermal": 0.0,
                "hydro": 45.0,
                "nuclear": 0.0,
                "oil": 0.0,
                "solar": 2493.0,
                "unknown": 166.0,
                "wind": 848.0
            },
            "productionCo2Intensities": {
                "biomass": 230,
                "coal": 820,
                "gas": 490,
                "geothermal": 38,
                "hydro": 24,
                "nuclear": 12,
                "oil": 650,
                "solar": 45,
                "unknown": 700,
                "wind": 11
            },
            "productionCo2IntensitySources": {
                "biomass": "IPCC 2014",
                "coal": "IPCC 2014",
                "gas": "IPCC 2014",
                "geothermal": "IPCC 2014",
                "hydro": "IPCC 2014",
                "nuclear": "IPCC 2014",
                "oil": "UK POST 2014",
                "solar": "IPCC 2014",
                "unknown": "assumes thermal (coal, gas, oil or biomass)",
                "wind": "IPCC 2014"
            },
            "renewableRatio": 0.47950000000000004,
            "renewableRatioProduction": 0.4778,
            "source": "entsoe.eu",
            "stateDatetime": "2022-07-11T09:00:00Z",
            "storage": {
                "battery": 0.0,
                "hydro": 0.0
            },
            "totalCo2Discharge": 0,
            "totalCo2Export": 1549917920.0,
            "totalCo2Import": 146124000.0,
            "totalCo2NetExchange": -1403793920.0,
            "totalCo2Production": 2500063000.0,
            "totalCo2Storage": 0,
            "totalConsumption": 3407.0,
            "totalDischarge": 0.0,
            "totalExport": 4817.0,
            "totalImport": 495.0,
            "totalProduction": 7729.0,
            "totalStorage": 0.0
        },
        {
            "_isFinestGranularity": true,
            "capacity": {
                "battery storage": 0.0,
                "biomass": 663.4,
                "coal": 2420.0,
                "gas": 9135.2,
                "geothermal": 0.0,
                "hydro": 1014.2,
                "hydro storage": 0.0,
                "nuclear": 0.0,
                "oil": 66.0,
                "solar": 4008.3,
                "unknown": 0.0,
                "wind": 5499.5
            },
            "co2intensity": 329.33,
            "co2intensityProduction": 331.52,
            "countryCode": "IT-SO",
            "dischargeCo2Intensities": {
                "battery": 341.85417092564336,
                "hydro": 341.85417092564336
            },
            "dischargeCo2IntensitySources": {
                "battery": "electricityMap, 2021 average",
                "hydro": "electricityMap, 2021 average"
            },
            "estimationMethod": 0.0,
            "exchange": {
                "GR": 495.0,
                "IT-CSO": -4693.0,
                "IT-SIC": 9.0
            },
            "exchangeCapacities": {
                "GR": [
                    -500.0,
                    500.0
                ]
            },
            "exchangeCo2Intensities": {
                "GR": 296.95,
                "IT-CSO": 329.33,
                "IT-SIC": 333.47
            },
            "fossilFuelRatio": 0.5315,
            "fossilFuelRatioProduction": 0.5341,
            "maxCapacity": 9135.2,
            "maxDischarge": 0,
            "maxExport": 4693.0,
            "maxExportCapacity": 500.0,
            "maxImport": 495.0,
            "maxImportCapacity": 500.0,
            "maxProduction": 2835.0,
            "maxStorage": 0,
            "maxStorageCapacity": 0.0,
            "price": {
                "currency": "EUR",
                "value": 404.1
            },
            "production": {
                "biomass": 311.0,
                "coal": 895.0,
                "gas": 2835.0,
                "geothermal": 0.0,
                "hydro": 45.0,
                "nuclear": 0.0,
                "oil": 0.0,
                "solar": 2152.0,
                "unknown": 165.0,
                "wind": 890.0
            },
            "productionCo2Intensities": {
                "biomass": 230,
                "coal": 820,
                "gas": 490,
                "geothermal": 38,
                "hydro": 24,
                "nuclear": 12,
                "oil": 650,
                "solar": 45,
                "unknown": 700,
                "wind": 11
            },
            "productionCo2IntensitySources": {
                "biomass": "IPCC 2014",
                "coal": "IPCC 2014",
                "gas": "IPCC 2014",
                "geothermal": "IPCC 2014",
                "hydro": "IPCC 2014",
                "nuclear": "IPCC 2014",
                "oil": "UK POST 2014",
                "solar": "IPCC 2014",
                "unknown": "assumes thermal (coal, gas, oil or biomass)",
                "wind": "IPCC 2014"
            },
            "renewableRatio": 0.4681,
            "renewableRatioProduction": 0.46590000000000004,
            "source": "entsoe.eu",
            "stateDatetime": "2022-07-11T10:00:00Z",
            "storage": {
                "battery": 0.0,
                "hydro": 0.0
            },
            "totalCo2Discharge": 0,
            "totalCo2Export": 1545545690.0,
            "totalCo2Import": 149991480.0,
            "totalCo2NetExchange": -1395554210.0,
            "totalCo2Production": 2417790000.0,
            "totalCo2Storage": 0,
            "totalConsumption": 3104.0,
            "totalDischarge": 0.0,
            "totalExport": 4693.0,
            "totalImport": 504.0,
            "totalProduction": 7293.0,
            "totalStorage": 0.0
        },
        {
            "_isFinestGranularity": true,
            "capacity": {
                "battery storage": 0.0,
                "biomass": 663.4,
                "coal": 2420.0,
                "gas": 9135.2,
                "geothermal": 0.0,
                "hydro": 1014.2,
                "hydro storage": 0.0,
                "nuclear": 0.0,
                "oil": 66.0,
                "solar": 4008.3,
                "unknown": 0.0,
                "wind": 5499.5
            },
            "co2intensity": 325.38,
            "co2intensityProduction": 326.65,
            "countryCode": "IT-SO",
            "dischargeCo2Intensities": {
                "battery": 341.85417092564336,
                "hydro": 341.85417092564336
            },
            "dischargeCo2IntensitySources": {
                "battery": "electricityMap, 2021 average",
                "hydro": "electricityMap, 2021 average"
            },
            "estimationMethod": 0.0,
            "exchange": {
                "GR": 495.0,
                "IT-CSO": -5108.0,
                "IT-SIC": -20.0
            },
            "exchangeCapacities": {
                "GR": [
                    -500.0,
                    500.0
                ]
            },
            "exchangeCo2Intensities": {
                "GR": 305.24,
                "IT-CSO": 325.38,
                "IT-SIC": 325.38
            },
            "fossilFuelRatio": 0.5303,
            "fossilFuelRatioProduction": 0.5315,
            "maxCapacity": 9135.2,
            "maxDischarge": 0,
            "maxExport": 5108.0,
            "maxExportCapacity": 500.0,
            "maxImport": 495.0,
            "maxImportCapacity": 500.0,
            "maxProduction": 3128.0,
            "maxStorage": 0,
            "maxStorageCapacity": 0.0,
            "price": {
                "currency": "EUR",
                "value": 405.88
            },
            "production": {
                "biomass": 311.0,
                "coal": 892.0,
                "gas": 3128.0,
                "geothermal": 0.0,
                "hydro": 45.0,
                "nuclear": 0.0,
                "oil": 0.0,
                "solar": 2429.0,
                "unknown": 168.0,
                "wind": 906.0
            },
            "productionCo2Intensities": {
                "biomass": 230,
                "coal": 820,
                "gas": 490,
                "geothermal": 38,
                "hydro": 24,
                "nuclear": 12,
                "oil": 650,
                "solar": 45,
                "unknown": 700,
                "wind": 11
            },
            "productionCo2IntensitySources": {
                "biomass": "IPCC 2014",
                "coal": "IPCC 2014",
                "gas": "IPCC 2014",
                "geothermal": "IPCC 2014",
                "hydro": "IPCC 2014",
                "nuclear": "IPCC 2014",
                "oil": "UK POST 2014",
                "solar": "IPCC 2014",
                "unknown": "assumes thermal (coal, gas, oil or biomass)",
                "wind": "IPCC 2014"
            },
            "renewableRatio": 0.4694,
            "renewableRatioProduction": 0.4685,
            "source": "entsoe.eu",
            "stateDatetime": "2022-07-11T11:00:00Z",
            "storage": {
                "battery": 0.0,
                "hydro": 0.0
            },
            "totalCo2Discharge": 0,
            "totalCo2Export": 1668548640.0,
            "totalCo2Import": 151093800.0,
            "totalCo2NetExchange": -1517454840.0,
            "totalCo2Production": 2573641000.0,
            "totalCo2Storage": 0,
            "totalConsumption": 3246.0,
            "totalDischarge": 0.0,
            "totalExport": 5128.0,
            "totalImport": 495.0,
            "totalProduction": 7879.0,
            "totalStorage": 0.0
        },
        {
            "_isFinestGranularity": true,
            "capacity": {
                "battery storage": 0.0,
                "biomass": 663.4,
                "coal": 2420.0,
                "gas": 9135.2,
                "geothermal": 0.0,
                "hydro": 1014.2,
                "hydro storage": 0.0,
                "nuclear": 0.0,
                "oil": 66.0,
                "solar": 4008.3,
                "unknown": 0.0,
                "wind": 5499.5
            },
            "co2intensity": 323.85,
            "co2intensityProduction": 324.03,
            "countryCode": "IT-SO",
            "dischargeCo2Intensities": {
                "battery": 341.85417092564336,
                "hydro": 341.85417092564336
            },
            "dischargeCo2IntensitySources": {
                "battery": "electricityMap, 2021 average",
                "hydro": "electricityMap, 2021 average"
            },
            "estimationMethod": 0.0,
            "exchange": {
                "GR": 495.0,
                "IT-CSO": -4556.0,
                "IT-SIC": -139.0
            },
            "exchangeCapacities": {
                "GR": [
                    -500.0,
                    500.0
                ]
            },
            "exchangeCo2Intensities": {
                "GR": 321.18,
                "IT-CSO": 323.85,
                "IT-SIC": 323.85
            },
            "fossilFuelRatio": 0.5199,
            "fossilFuelRatioProduction": 0.5183,
            "maxCapacity": 9135.2,
            "maxDischarge": 0,
            "maxExport": 4556.0,
            "maxExportCapacity": 500.0,
            "maxImport": 495.0,
            "maxImportCapacity": 500.0,
            "maxProduction": 2755.0,
            "maxStorage": 0,
            "maxStorageCapacity": 0.0,
            "price": {
                "currency": "EUR",
                "value": 413.0
            },
            "production": {
                "biomass": 309.0,
                "coal": 891.0,
                "gas": 2755.0,
                "geothermal": 0.0,
                "hydro": 45.0,
                "nuclear": 0.0,
                "oil": 0.0,
                "solar": 2315.0,
                "unknown": 170.0,
                "wind": 877.0
            },
            "productionCo2Intensities": {
                "biomass": 230,
                "coal": 820,
                "gas": 490,
                "geothermal": 38,
                "hydro": 24,
                "nuclear": 12,
                "oil": 650,
                "solar": 45,
                "unknown": 700,
                "wind": 11
            },
            "productionCo2IntensitySources": {
                "biomass": "IPCC 2014",
                "coal": "IPCC 2014",
                "gas": "IPCC 2014",
                "geothermal": "IPCC 2014",
                "hydro": "IPCC 2014",
                "nuclear": "IPCC 2014",
                "oil": "UK POST 2014",
                "solar": "IPCC 2014",
                "unknown": "assumes thermal (coal, gas, oil or biomass)",
                "wind": "IPCC 2014"
            },
            "renewableRatio": 0.4797,
            "renewableRatioProduction": 0.4817,
            "source": "entsoe.eu",
            "stateDatetime": "2022-07-11T12:00:00Z",
            "storage": {
                "battery": 0.0,
                "hydro": 0.0
            },
            "totalCo2Discharge": 0,
            "totalCo2Export": 1520475750.0,
            "totalCo2Import": 158984100.0,
            "totalCo2NetExchange": -1361491650.0,
            "totalCo2Production": 2385542000.0,
            "totalCo2Storage": 0,
            "totalConsumption": 3162.0,
            "totalDischarge": 0.0,
            "totalExport": 4695.0,
            "totalImport": 495.0,
            "totalProduction": 7362.0,
            "totalStorage": 0.0
        },
        {
            "_isFinestGranularity": true,
            "capacity": {
                "battery storage": 0.0,
                "biomass": 663.4,
                "coal": 2420.0,
                "gas": 9135.2,
                "geothermal": 0.0,
                "hydro": 1014.2,
                "hydro storage": 0.0,
                "nuclear": 0.0,
                "oil": 66.0,
                "solar": 4008.3,
                "unknown": 0.0,
                "wind": 5499.5
            },
            "co2intensity": 336.59,
            "co2intensityProduction": 336.56,
            "countryCode": "IT-SO",
            "dischargeCo2Intensities": {
                "battery": 341.85417092564336,
                "hydro": 341.85417092564336
            },
            "dischargeCo2IntensitySources": {
                "battery": "electricityMap, 2021 average",
                "hydro": "electricityMap, 2021 average"
            },
            "estimationMethod": 0.0,
            "exchange": {
                "GR": 495.0,
                "IT-CSO": -4479.0,
                "IT-SIC": -242.0
            },
            "exchangeCapacities": {
                "GR": [
                    -500.0,
                    500.0
                ]
            },
            "exchangeCo2Intensities": {
                "GR": 337.08,
                "IT-CSO": 336.59,
                "IT-SIC": 336.59
            },
            "fossilFuelRatio": 0.5492,
            "fossilFuelRatioProduction": 0.5474,
            "maxCapacity": 9135.2,
            "maxDischarge": 0,
            "maxExport": 4479.0,
            "maxExportCapacity": 500.0,
            "maxImport": 495.0,
            "maxImportCapacity": 500.0,
            "maxProduction": 3047.0,
            "maxStorage": 0,
            "maxStorageCapacity": 0.0,
            "price": {
                "currency": "EUR",
                "value": 413.24
            },
            "production": {
                "biomass": 309.0,
                "coal": 892.0,
                "gas": 3047.0,
                "geothermal": 0.0,
                "hydro": 46.0,
                "nuclear": 0.0,
                "oil": 0.0,
                "solar": 2247.0,
                "unknown": 180.0,
                "wind": 804.0
            },
            "productionCo2Intensities": {
                "biomass": 230,
                "coal": 820,
                "gas": 490,
                "geothermal": 38,
                "hydro": 24,
                "nuclear": 12,
                "oil": 650,
                "solar": 45,
                "unknown": 700,
                "wind": 11
            },
            "productionCo2IntensitySources": {
                "biomass": "IPCC 2014",
                "coal": "IPCC 2014",
                "gas": "IPCC 2014",
                "geothermal": "IPCC 2014",
                "hydro": "IPCC 2014",
                "nuclear": "IPCC 2014",
                "oil": "UK POST 2014",
                "solar": "IPCC 2014",
                "unknown": "assumes thermal (coal, gas, oil or biomass)",
                "wind": "IPCC 2014"
            },
            "renewableRatio": 0.45039999999999997,
            "renewableRatioProduction": 0.4526,
            "source": "entsoe.eu",
            "stateDatetime": "2022-07-11T13:00:00Z",
            "storage": {
                "battery": 0.0,
                "hydro": 0.0
            },
            "totalCo2Discharge": 0,
            "totalCo2Export": 1589041390.0,
            "totalCo2Import": 166854600.0,
            "totalCo2NetExchange": -1422186790.0,
            "totalCo2Production": 2532603000.0,
            "totalCo2Storage": 0,
            "totalConsumption": 3299.0,
            "totalDischarge": 0.0,
            "totalExport": 4721.0,
            "totalImport": 495.0,
            "totalProduction": 7525.0,
            "totalStorage": 0.0
        },
        {
            "_isFinestGranularity": true,
            "capacity": {
                "battery storage": 0.0,
                "biomass": 663.4,
                "coal": 2420.0,
                "gas": 9135.2,
                "geothermal": 0.0,
                "hydro": 1014.2,
                "hydro storage": 0.0,
                "nuclear": 0.0,
                "oil": 66.0,
                "solar": 4008.3,
                "unknown": 0.0,
                "wind": 5499.5
            },
            "co2intensity": 354.2,
            "co2intensityProduction": 354.29,
            "countryCode": "IT-SO",
            "dischargeCo2Intensities": {
                "battery": 341.85417092564336,
                "hydro": 341.85417092564336
            },
            "dischargeCo2IntensitySources": {
                "battery": "electricityMap, 2021 average",
                "hydro": "electricityMap, 2021 average"
            },
            "estimationMethod": 0.0,
            "exchange": {
                "GR": 495.0,
                "IT-CSO": -4502.0,
                "IT-SIC": -122.0
            },
            "exchangeCapacities": {
                "GR": [
                    -500.0,
                    500.0
                ]
            },
            "exchangeCo2Intensities": {
                "GR": 352.94,
                "IT-CSO": 354.2,
                "IT-SIC": 354.2
            },
            "fossilFuelRatio": 0.5901,
            "fossilFuelRatioProduction": 0.589,
            "maxCapacity": 9135.2,
            "maxDischarge": 0,
            "maxExport": 4502.0,
            "maxExportCapacity": 500.0,
            "maxImport": 495.0,
            "maxImportCapacity": 500.0,
            "maxProduction": 3413.0,
            "maxStorage": 0,
            "maxStorageCapacity": 0.0,
            "price": {
                "currency": "EUR",
                "value": 423.24
            },
            "production": {
                "biomass": 313.0,
                "coal": 890.0,
                "gas": 3413.0,
                "geothermal": 0.0,
                "hydro": 49.0,
                "nuclear": 0.0,
                "oil": 0.0,
                "solar": 1965.0,
                "unknown": 162.0,
                "wind": 789.0
            },
            "productionCo2Intensities": {
                "biomass": 230,
                "coal": 820,
                "gas": 490,
                "geothermal": 38,
                "hydro": 24,
                "nuclear": 12,
                "oil": 650,
                "solar": 45,
                "unknown": 700,
                "wind": 11
            },
            "productionCo2IntensitySources": {
                "biomass": "IPCC 2014",
                "coal": "IPCC 2014",
                "gas": "IPCC 2014",
                "geothermal": "IPCC 2014",
                "hydro": "IPCC 2014",
                "nuclear": "IPCC 2014",
                "oil": "UK POST 2014",
                "solar": "IPCC 2014",
                "unknown": "assumes thermal (coal, gas, oil or biomass)",
                "wind": "IPCC 2014"
            },
            "renewableRatio": 0.4093,
            "renewableRatioProduction": 0.41100000000000003,
            "source": "entsoe.eu",
            "stateDatetime": "2022-07-11T14:00:00Z",
            "storage": {
                "battery": 0.0,
                "hydro": 0.0
            },
            "totalCo2Discharge": 0,
            "totalCo2Export": 1637820800.0,
            "totalCo2Import": 174705300.0,
            "totalCo2NetExchange": -1463115500.0,
            "totalCo2Production": 2685840000.0,
            "totalCo2Storage": 0,
            "totalConsumption": 3452.0,
            "totalDischarge": 0.0,
            "totalExport": 4624.0,
            "totalImport": 495.0,
            "totalProduction": 7581.0,
            "totalStorage": 0.0
        },
        {
            "_isFinestGranularity": true,
            "capacity": {
                "battery storage": 0.0,
                "biomass": 663.4,
                "coal": 2420.0,
                "gas": 9135.2,
                "geothermal": 0.0,
                "hydro": 1014.2,
                "hydro storage": 0.0,
                "nuclear": 0.0,
                "oil": 66.0,
                "solar": 4008.3,
                "unknown": 0.0,
                "wind": 5499.5
            },
            "co2intensity": 366.82,
            "co2intensityProduction": 365.69,
            "countryCode": "IT-SO",
            "dischargeCo2Intensities": {
                "battery": 341.85417092564336,
                "hydro": 341.85417092564336
            },
            "dischargeCo2IntensitySources": {
                "battery": "electricityMap, 2021 average",
                "hydro": "electricityMap, 2021 average"
            },
            "estimationMethod": 0.0,
            "exchange": {
                "GR": 495.0,
                "IT-CSO": -4198.0,
                "IT-SIC": -298.0
            },
            "exchangeCapacities": {
                "GR": [
                    -500.0,
                    500.0
                ]
            },
            "exchangeCo2Intensities": {
                "GR": 384.11,
                "IT-CSO": 366.82,
                "IT-SIC": 366.82
            },
            "fossilFuelRatio": 0.6206,
            "fossilFuelRatioProduction": 0.6177,
            "maxCapacity": 9135.2,
            "maxDischarge": 0,
            "maxExport": 4198.0,
            "maxExportCapacity": 500.0,
            "maxImport": 495.0,
            "maxImportCapacity": 500.0,
            "maxProduction": 3641.0,
            "maxStorage": 0,
            "maxStorageCapacity": 0.0,
            "price": {
                "currency": "EUR",
                "value": 433.03
            },
            "production": {
                "biomass": 312.0,
                "coal": 871.0,
                "gas": 3641.0,
                "geothermal": 0.0,
                "hydro": 396.0,
                "nuclear": 0.0,
                "oil": 0.0,
                "solar": 1450.0,
                "unknown": 170.0,
                "wind": 740.0
            },
            "productionCo2Intensities": {
                "biomass": 230,
                "coal": 820,
                "gas": 490,
                "geothermal": 38,
                "hydro": 24,
                "nuclear": 12,
                "oil": 650,
                "solar": 45,
                "unknown": 700,
                "wind": 11
            },
            "productionCo2IntensitySources": {
                "biomass": "IPCC 2014",
                "coal": "IPCC 2014",
                "gas": "IPCC 2014",
                "geothermal": "IPCC 2014",
                "hydro": "IPCC 2014",
                "nuclear": "IPCC 2014",
                "oil": "UK POST 2014",
                "solar": "IPCC 2014",
                "unknown": "assumes thermal (coal, gas, oil or biomass)",
                "wind": "IPCC 2014"
            },
            "renewableRatio": 0.3787,
            "renewableRatioProduction": 0.3823,
            "source": "entsoe.eu",
            "stateDatetime": "2022-07-11T15:00:00Z",
            "storage": {
                "battery": 0.0,
                "hydro": 0.0
            },
            "totalCo2Discharge": 0,
            "totalCo2Export": 1649222720.0,
            "totalCo2Import": 190134450.0,
            "totalCo2NetExchange": -1459088270.0,
            "totalCo2Production": 2771964000.0,
            "totalCo2Storage": 0,
            "totalConsumption": 3579.0,
            "totalDischarge": 0.0,
            "totalExport": 4496.0,
            "totalImport": 495.0,
            "totalProduction": 7580.0,
            "totalStorage": 0.0
        },
        {
            "_isFinestGranularity": true,
            "capacity": {
                "battery storage": 0.0,
                "biomass": 663.4,
                "coal": 2420.0,
                "gas": 9135.2,
                "geothermal": 0.0,
                "hydro": 1014.2,
                "hydro storage": 0.0,
                "nuclear": 0.0,
                "oil": 66.0,
                "solar": 4008.3,
                "unknown": 0.0,
                "wind": 5499.5
            },
            "co2intensity": 411.2,
            "co2intensityProduction": 412.21,
            "countryCode": "IT-SO",
            "dischargeCo2Intensities": {
                "battery": 341.85417092564336,
                "hydro": 341.85417092564336
            },
            "dischargeCo2IntensitySources": {
                "battery": "electricityMap, 2021 average",
                "hydro": "electricityMap, 2021 average"
            },
            "estimationMethod": 0.0,
            "exchange": {
                "GR": 495.0,
                "IT-CSO": -4212.0,
                "IT-SIC": -358.0
            },
            "exchangeCapacities": {
                "GR": [
                    -500.0,
                    500.0
                ]
            },
            "exchangeCo2Intensities": {
                "GR": 395.8,
                "IT-CSO": 411.2,
                "IT-SIC": 411.2
            },
            "fossilFuelRatio": 0.7132999999999999,
            "fossilFuelRatioProduction": 0.7161,
            "maxCapacity": 9135.2,
            "maxDischarge": 0,
            "maxExport": 4212.0,
            "maxExportCapacity": 500.0,
            "maxImport": 495.0,
            "maxImportCapacity": 500.0,
            "maxProduction": 4329.0,
            "maxStorage": 0,
            "maxStorageCapacity": 0.0,
            "price": {
                "currency": "EUR",
                "value": 450.79
            },
            "production": {
                "biomass": 315.0,
                "coal": 919.0,
                "gas": 4329.0,
                "geothermal": 0.0,
                "hydro": 450.0,
                "nuclear": 0.0,
                "oil": 0.0,
                "solar": 732.0,
                "unknown": 184.0,
                "wind": 657.0
            },
            "productionCo2Intensities": {
                "biomass": 230,
                "coal": 820,
                "gas": 490,
                "geothermal": 38,
                "hydro": 24,
                "nuclear": 12,
                "oil": 650,
                "solar": 45,
                "unknown": 700,
                "wind": 11
            },
            "productionCo2IntensitySources": {
                "biomass": "IPCC 2014",
                "coal": "IPCC 2014",
                "gas": "IPCC 2014",
                "geothermal": "IPCC 2014",
                "hydro": "IPCC 2014",
                "nuclear": "IPCC 2014",
                "oil": "UK POST 2014",
                "solar": "IPCC 2014",
                "unknown": "assumes thermal (coal, gas, oil or biomass)",
                "wind": "IPCC 2014"
            },
            "renewableRatio": 0.2861,
            "renewableRatioProduction": 0.2839,
            "source": "entsoe.eu",
            "stateDatetime": "2022-07-11T16:00:00Z",
            "storage": {
                "battery": 0.0,
                "hydro": 0.0
            },
            "totalCo2Discharge": 0,
            "totalCo2Export": 1879184000.0,
            "totalCo2Import": 195921000.0,
            "totalCo2NetExchange": -1683263000.0,
            "totalCo2Production": 3127007000.0,
            "totalCo2Storage": 0,
            "totalConsumption": 3511.0,
            "totalDischarge": 0.0,
            "totalExport": 4570.0,
            "totalImport": 495.0,
            "totalProduction": 7586.0,
            "totalStorage": 0.0
        },
        {
            "_isFinestGranularity": true,
            "capacity": {
                "battery storage": 0.0,
                "biomass": 663.4,
                "coal": 2420.0,
                "gas": 9135.2,
                "geothermal": 0.0,
                "hydro": 1014.2,
                "hydro storage": 0.0,
                "nuclear": 0.0,
                "oil": 66.0,
                "solar": 4008.3,
                "unknown": 0.0,
                "wind": 5499.5
            },
            "co2intensity": 448.28,
            "co2intensityProduction": 450.92,
            "countryCode": "IT-SO",
            "dischargeCo2Intensities": {
                "battery": 341.85417092564336,
                "hydro": 341.85417092564336
            },
            "dischargeCo2IntensitySources": {
                "battery": "electricityMap, 2021 average",
                "hydro": "electricityMap, 2021 average"
            },
            "estimationMethod": 0.0,
            "exchange": {
                "GR": 495.0,
                "IT-CSO": -3821.0,
                "IT-SIC": -573.0
            },
            "exchangeCapacities": {
                "GR": [
                    -500.0,
                    500.0
                ]
            },
            "exchangeCo2Intensities": {
                "GR": 409.09,
                "IT-CSO": 448.28,
                "IT-SIC": 448.28
            },
            "fossilFuelRatio": 0.7888,
            "fossilFuelRatioProduction": 0.7957,
            "maxCapacity": 9135.2,
            "maxDischarge": 0,
            "maxExport": 3821.0,
            "maxExportCapacity": 500.0,
            "maxImport": 495.0,
            "maxImportCapacity": 500.0,
            "maxProduction": 4713.0,
            "maxStorage": 0,
            "maxStorageCapacity": 0.0,
            "price": {
                "currency": "EUR",
                "value": 480.0
            },
            "production": {
                "biomass": 313.0,
                "coal": 945.0,
                "gas": 4713.0,
                "geothermal": 0.0,
                "hydro": 463.0,
                "nuclear": 0.0,
                "oil": 0.0,
                "solar": 168.0,
                "unknown": 189.0,
                "wind": 557.0
            },
            "productionCo2Intensities": {
                "biomass": 230,
                "coal": 820,
                "gas": 490,
                "geothermal": 38,
                "hydro": 24,
                "nuclear": 12,
                "oil": 650,
                "solar": 45,
                "unknown": 700,
                "wind": 11
            },
            "productionCo2IntensitySources": {
                "biomass": "IPCC 2014",
                "coal": "IPCC 2014",
                "gas": "IPCC 2014",
                "geothermal": "IPCC 2014",
                "hydro": "IPCC 2014",
                "nuclear": "IPCC 2014",
                "oil": "UK POST 2014",
                "solar": "IPCC 2014",
                "unknown": "assumes thermal (coal, gas, oil or biomass)",
                "wind": "IPCC 2014"
            },
            "renewableRatio": 0.21050000000000002,
            "renewableRatioProduction": 0.2043,
            "source": "entsoe.eu",
            "stateDatetime": "2022-07-11T17:00:00Z",
            "storage": {
                "battery": 0.0,
                "hydro": 0.0
            },
            "totalCo2Discharge": 0,
            "totalCo2Export": 1969742320.0,
            "totalCo2Import": 202499550.0,
            "totalCo2NetExchange": -1767242770.0,
            "totalCo2Production": 3313359000.0,
            "totalCo2Storage": 0,
            "totalConsumption": 3449.0,
            "totalDischarge": 0.0,
            "totalExport": 4394.0,
            "totalImport": 495.0,
            "totalProduction": 7348.0,
            "totalStorage": 0.0
        },
        {
            "_isFinestGranularity": true,
            "capacity": {
                "battery storage": 0.0,
                "biomass": 663.4,
                "coal": 2420.0,
                "gas": 9135.2,
                "geothermal": 0.0,
                "hydro": 1014.2,
                "hydro storage": 0.0,
                "nuclear": 0.0,
                "oil": 66.0,
                "solar": 4008.3,
                "unknown": 0.0,
                "wind": 5499.5
            },
            "co2intensity": 465.59,
            "co2intensityProduction": 469.22,
            "countryCode": "IT-SO",
            "dischargeCo2Intensities": {
                "battery": 341.85417092564336,
                "hydro": 341.85417092564336
            },
            "dischargeCo2IntensitySources": {
                "battery": "electricityMap, 2021 average",
                "hydro": "electricityMap, 2021 average"
            },
            "estimationMethod": 0.0,
            "exchange": {
                "GR": 483.0,
                "IT-CSO": -3224.0,
                "IT-SIC": -859.0
            },
            "exchangeCapacities": {
                "GR": [
                    -500.0,
                    500.0
                ]
            },
            "exchangeCo2Intensities": {
                "GR": 412.16,
                "IT-CSO": 465.59,
                "IT-SIC": 465.59
            },
            "fossilFuelRatio": 0.8240000000000001,
            "fossilFuelRatioProduction": 0.8327,
            "maxCapacity": 9135.2,
            "maxDischarge": 0,
            "maxExport": 3224.0,
            "maxExportCapacity": 500.0,
            "maxImport": 483.0,
            "maxImportCapacity": 500.0,
            "maxProduction": 4792.0,
            "maxStorage": 0,
            "maxStorageCapacity": 0.0,
            "price": {
                "currency": "EUR",
                "value": 480.0
            },
            "production": {
                "biomass": 312.0,
                "coal": 929.0,
                "gas": 4792.0,
                "geothermal": 0.0,
                "hydro": 472.0,
                "nuclear": 0.0,
                "oil": 0.0,
                "solar": 5.0,
                "unknown": 192.0,
                "wind": 399.0
            },
            "productionCo2Intensities": {
                "biomass": 230,
                "coal": 820,
                "gas": 490,
                "geothermal": 38,
                "hydro": 24,
                "nuclear": 12,
                "oil": 650,
                "solar": 45,
                "unknown": 700,
                "wind": 11
            },
            "productionCo2IntensitySources": {
                "biomass": "IPCC 2014",
                "coal": "IPCC 2014",
                "gas": "IPCC 2014",
                "geothermal": "IPCC 2014",
                "hydro": "IPCC 2014",
                "nuclear": "IPCC 2014",
                "oil": "UK POST 2014",
                "solar": "IPCC 2014",
                "unknown": "assumes thermal (coal, gas, oil or biomass)",
                "wind": "IPCC 2014"
            },
            "renewableRatio": 0.1754,
            "renewableRatioProduction": 0.1673,
            "source": "entsoe.eu",
            "stateDatetime": "2022-07-11T18:00:00Z",
            "storage": {
                "battery": 0.0,
                "hydro": 0.0
            },
            "totalCo2Discharge": 0,
            "totalCo2Export": 1901003970.0,
            "totalCo2Import": 199073280.0,
            "totalCo2NetExchange": -1701930690.0,
            "totalCo2Production": 3331962000.0,
            "totalCo2Storage": 0,
            "totalConsumption": 3501.0,
            "totalDischarge": 0.0,
            "totalExport": 4083.0,
            "totalImport": 483.0,
            "totalProduction": 7101.0,
            "totalStorage": 0.0
        },
        {
            "_isFinestGranularity": true,
            "capacity": {
                "battery storage": 0.0,
                "biomass": 663.4,
                "coal": 2420.0,
                "gas": 9135.2,
                "geothermal": 0.0,
                "hydro": 1014.2,
                "hydro storage": 0.0,
                "nuclear": 0.0,
                "oil": 66.0,
                "solar": 4008.3,
                "unknown": 0.0,
                "wind": 5499.5
            },
            "co2intensity": 493.64,
            "co2intensityProduction": 498.85,
            "countryCode": "IT-SO",
            "dischargeCo2Intensities": {
                "battery": 341.85417092564336,
                "hydro": 341.85417092564336
            },
            "dischargeCo2IntensitySources": {
                "battery": "electricityMap, 2021 average",
                "hydro": "electricityMap, 2021 average"
            },
            "estimationMethod": 0.0,
            "exchange": {
                "GR": 495.0,
                "IT-CSO": -2825.0,
                "IT-SIC": -951.0
            },
            "exchangeCapacities": {
                "GR": [
                    -500.0,
                    500.0
                ]
            },
            "exchangeCo2Intensities": {
                "GR": 423.08,
                "IT-CSO": 493.64,
                "IT-SIC": 493.64
            },
            "fossilFuelRatio": 0.8748999999999999,
            "fossilFuelRatioProduction": 0.8868,
            "maxCapacity": 9135.2,
            "maxDischarge": 0,
            "maxExport": 2825.0,
            "maxExportCapacity": 500.0,
            "maxImport": 495.0,
            "maxImportCapacity": 500.0,
            "maxProduction": 4813.0,
            "maxStorage": 0,
            "maxStorageCapacity": 0.0,
            "price": {
                "currency": "EUR",
                "value": 480.0
            },
            "production": {
                "biomass": 313.0,
                "coal": 947.0,
                "gas": 4813.0,
                "geothermal": 0.0,
                "hydro": 158.0,
                "nuclear": 0.0,
                "oil": 0.0,
                "solar": 0.0,
                "unknown": 192.0,
                "wind": 289.0
            },
            "productionCo2Intensities": {
                "biomass": 230,
                "coal": 820,
                "gas": 490,
                "geothermal": 38,
                "hydro": 24,
                "nuclear": 12,
                "oil": 650,
                "solar": 45,
                "unknown": 700,
                "wind": 11
            },
            "productionCo2IntensitySources": {
                "biomass": "IPCC 2014",
                "coal": "IPCC 2014",
                "gas": "IPCC 2014",
                "geothermal": "IPCC 2014",
                "hydro": "IPCC 2014",
                "nuclear": "IPCC 2014",
                "oil": "UK POST 2014",
                "solar": "IPCC 2014",
                "unknown": "assumes thermal (coal, gas, oil or biomass)",
                "wind": "IPCC 2014"
            },
            "renewableRatio": 0.1243,
            "renewableRatioProduction": 0.11320000000000001,
            "source": "entsoe.eu",
            "stateDatetime": "2022-07-11T19:00:00Z",
            "storage": {
                "battery": 0.0,
                "hydro": 0.0
            },
            "totalCo2Discharge": 0,
            "totalCo2Export": 1863984640.0,
            "totalCo2Import": 209424600.0,
            "totalCo2NetExchange": -1654560040.0,
            "totalCo2Production": 3348271000.0,
            "totalCo2Storage": 0,
            "totalConsumption": 3431.0,
            "totalDischarge": 0.0,
            "totalExport": 3776.0,
            "totalImport": 495.0,
            "totalProduction": 6712.0,
            "totalStorage": 0.0
        },
        {
            "_isFinestGranularity": true,
            "capacity": {
                "battery storage": 0.0,
                "biomass": 663.4,
                "coal": 2420.0,
                "gas": 9135.2,
                "geothermal": 0.0,
                "hydro": 1014.2,
                "hydro storage": 0.0,
                "nuclear": 0.0,
                "oil": 66.0,
                "solar": 4008.3,
                "unknown": 0.0,
                "wind": 5499.5
            },
            "co2intensity": 501.91,
            "co2intensityProduction": 507.28,
            "countryCode": "IT-SO",
            "dischargeCo2Intensities": {
                "battery": 341.85417092564336,
                "hydro": 341.85417092564336
            },
            "dischargeCo2IntensitySources": {
                "battery": "electricityMap, 2021 average",
                "hydro": "electricityMap, 2021 average"
            },
            "estimationMethod": 0.0,
            "exchange": {
                "GR": 495.0,
                "IT-CSO": -3195.0,
                "IT-SIC": -757.0
            },
            "exchangeCapacities": {
                "GR": [
                    -500.0,
                    500.0
                ]
            },
            "exchangeCo2Intensities": {
                "GR": 430.44,
                "IT-CSO": 501.91,
                "IT-SIC": 501.91
            },
            "fossilFuelRatio": 0.8906999999999999,
            "fossilFuelRatioProduction": 0.9006000000000001,
            "maxCapacity": 9135.2,
            "maxDischarge": 0,
            "maxExport": 3195.0,
            "maxExportCapacity": 500.0,
            "maxImport": 495.0,
            "maxImportCapacity": 500.0,
            "maxProduction": 4786.0,
            "maxStorage": 0,
            "maxStorageCapacity": 0.0,
            "price": {
                "currency": "EUR",
                "value": 450.79
            },
            "production": {
                "biomass": 315.0,
                "coal": 964.0,
                "gas": 4786.0,
                "geothermal": 0.0,
                "hydro": 112.0,
                "nuclear": 0.0,
                "oil": 0.0,
                "solar": 0.0,
                "unknown": 186.0,
                "wind": 228.0
            },
            "productionCo2Intensities": {
                "biomass": 230,
                "coal": 820,
                "gas": 490,
                "geothermal": 38,
                "hydro": 24,
                "nuclear": 12,
                "oil": 650,
                "solar": 45,
                "unknown": 700,
                "wind": 11
            },
            "productionCo2IntensitySources": {
                "biomass": "IPCC 2014",
                "coal": "IPCC 2014",
                "gas": "IPCC 2014",
                "geothermal": "IPCC 2014",
                "hydro": "IPCC 2014",
                "nuclear": "IPCC 2014",
                "oil": "UK POST 2014",
                "solar": "IPCC 2014",
                "unknown": "assumes thermal (coal, gas, oil or biomass)",
                "wind": "IPCC 2014"
            },
            "renewableRatio": 0.1084,
            "renewableRatioProduction": 0.09939999999999999,
            "source": "entsoe.eu",
            "stateDatetime": "2022-07-11T20:00:00Z",
            "storage": {
                "battery": 0.0,
                "hydro": 0.0
            },
            "totalCo2Discharge": 0,
            "totalCo2Export": 1983548320.0,
            "totalCo2Import": 213067800.0,
            "totalCo2NetExchange": -1770480520.0,
            "totalCo2Production": 3343466000.0,
            "totalCo2Storage": 0,
            "totalConsumption": 3134.0,
            "totalDischarge": 0.0,
            "totalExport": 3952.0,
            "totalImport": 495.0,
            "totalProduction": 6591.0,
            "totalStorage": 0.0
        },
        {
            "_isFinestGranularity": true,
            "capacity": {
                "battery storage": 0.0,
                "biomass": 663.4,
                "coal": 2420.0,
                "gas": 9135.2,
                "geothermal": 0.0,
                "hydro": 1014.2,
                "hydro storage": 0.0,
                "nuclear": 0.0,
                "oil": 66.0,
                "solar": 4008.3,
                "unknown": 0.0,
                "wind": 5499.5
            },
            "co2intensity": 503.59,
            "co2intensityProduction": 507.79,
            "countryCode": "IT-SO",
            "dischargeCo2Intensities": {
                "battery": 341.85417092564336,
                "hydro": 341.85417092564336
            },
            "dischargeCo2IntensitySources": {
                "battery": "electricityMap, 2021 average",
                "hydro": "electricityMap, 2021 average"
            },
            "estimationMethod": 0.0,
            "exchange": {
                "GR": 495.0,
                "IT-CSO": -3613.0,
                "IT-SIC": -315.0
            },
            "exchangeCapacities": {
                "GR": [
                    -500.0,
                    500.0
                ]
            },
            "exchangeCo2Intensities": {
                "GR": 450.32,
                "IT-CSO": 503.59,
                "IT-SIC": 503.59
            },
            "fossilFuelRatio": 0.8911,
            "fossilFuelRatioProduction": 0.8986,
            "maxCapacity": 9135.2,
            "maxDischarge": 0,
            "maxExport": 3613.0,
            "maxExportCapacity": 500.0,
            "maxImport": 495.0,
            "maxImportCapacity": 500.0,
            "maxProduction": 4529.0,
            "maxStorage": 0,
            "maxStorageCapacity": 0.0,
            "price": {
                "currency": "EUR",
                "value": 425.0
            },
            "production": {
                "biomass": 314.0,
                "coal": 936.0,
                "gas": 4529.0,
                "geothermal": 0.0,
                "hydro": 111.0,
                "nuclear": 0.0,
                "oil": 0.0,
                "solar": 0.0,
                "unknown": 180.0,
                "wind": 212.0
            },
            "productionCo2Intensities": {
                "biomass": 230,
                "coal": 820,
                "gas": 490,
                "geothermal": 38,
                "hydro": 24,
                "nuclear": 12,
                "oil": 650,
                "solar": 45,
                "unknown": 700,
                "wind": 11
            },
            "productionCo2IntensitySources": {
                "biomass": "IPCC 2014",
                "coal": "IPCC 2014",
                "gas": "IPCC 2014",
                "geothermal": "IPCC 2014",
                "hydro": "IPCC 2014",
                "nuclear": "IPCC 2014",
                "oil": "UK POST 2014",
                "solar": "IPCC 2014",
                "unknown": "assumes thermal (coal, gas, oil or biomass)",
                "wind": "IPCC 2014"
            },
            "renewableRatio": 0.1079,
            "renewableRatioProduction": 0.1014,
            "source": "entsoe.eu",
            "stateDatetime": "2022-07-11T21:00:00Z",
            "storage": {
                "battery": 0.0,
                "hydro": 0.0
            },
            "totalCo2Discharge": 0,
            "totalCo2Export": 1978101520.0,
            "totalCo2Import": 222908400.0,
            "totalCo2NetExchange": -1755193120.0,
            "totalCo2Production": 3189946000.0,
            "totalCo2Storage": 0,
            "totalConsumption": 2849.0,
            "totalDischarge": 0.0,
            "totalExport": 3928.0,
            "totalImport": 495.0,
            "totalProduction": 6282.0,
            "totalStorage": 0.0
        },
        {
            "_isFinestGranularity": true,
            "capacity": {
                "battery storage": 0.0,
                "biomass": 663.4,
                "coal": 2420.0,
                "gas": 9135.2,
                "geothermal": 0.0,
                "hydro": 1014.2,
                "hydro storage": 0.0,
                "nuclear": 0.0,
                "oil": 66.0,
                "solar": 4008.3,
                "unknown": 0.0,
                "wind": 5499.5
            },
            "co2intensity": 507.3,
            "co2intensityProduction": 510.05,
            "countryCode": "IT-SO",
            "dischargeCo2Intensities": {
                "battery": 341.85417092564336,
                "hydro": 341.85417092564336
            },
            "dischargeCo2IntensitySources": {
                "battery": "electricityMap, 2021 average",
                "hydro": "electricityMap, 2021 average"
            },
            "estimationMethod": 0.0,
            "exchange": {
                "GR": 500.0,
                "IT-CSO": -3034.0,
                "IT-SIC": -258.0
            },
            "exchangeCapacities": {
                "GR": [
                    -500.0,
                    500.0
                ]
            },
            "exchangeCo2Intensities": {
                "GR": 476.95,
                "IT-CSO": 507.3,
                "IT-SIC": 507.3
            },
            "fossilFuelRatio": 0.8771,
            "fossilFuelRatioProduction": 0.8787,
            "maxCapacity": 9135.2,
            "maxDischarge": 0,
            "maxExport": 3034.0,
            "maxExportCapacity": 500.0,
            "maxImport": 500.0,
            "maxImportCapacity": 500.0,
            "maxProduction": 3693.0,
            "maxStorage": 0,
            "maxStorageCapacity": 0.0,
            "price": {
                "currency": "EUR",
                "value": 411.27
            },
            "production": {
                "biomass": 311.0,
                "coal": 991.0,
                "gas": 3693.0,
                "geothermal": 0.0,
                "hydro": 109.0,
                "nuclear": 0.0,
                "oil": 0.0,
                "solar": 2.0,
                "unknown": 164.0,
                "wind": 247.0
            },
            "productionCo2Intensities": {
                "biomass": 230,
                "coal": 820,
                "gas": 490,
                "geothermal": 38,
                "hydro": 24,
                "nuclear": 12,
                "oil": 650,
                "solar": 45,
                "unknown": 700,
                "wind": 11
            },
            "productionCo2IntensitySources": {
                "biomass": "IPCC 2014",
                "coal": "IPCC 2014",
                "gas": "IPCC 2014",
                "geothermal": "IPCC 2014",
                "hydro": "IPCC 2014",
                "nuclear": "IPCC 2014",
                "oil": "UK POST 2014",
                "solar": "IPCC 2014",
                "unknown": "assumes thermal (coal, gas, oil or biomass)",
                "wind": "IPCC 2014"
            },
            "renewableRatio": 0.1216,
            "renewableRatioProduction": 0.1213,
            "source": "entsoe.eu",
            "stateDatetime": "2022-07-11T22:00:00Z",
            "storage": {
                "battery": 0.0,
                "hydro": 0.0
            },
            "totalCo2Discharge": 0,
            "totalCo2Export": 1670031600.0,
            "totalCo2Import": 238475000.0,
            "totalCo2NetExchange": -1431556600.0,
            "totalCo2Production": 2813943000.0,
            "totalCo2Storage": 0,
            "totalConsumption": 2725.0,
            "totalDischarge": 0.0,
            "totalExport": 3292.0,
            "totalImport": 500.0,
            "totalProduction": 5517.0,
            "totalStorage": 0.0
        },
        {
            "_isFinestGranularity": true,
            "capacity": {
                "battery storage": 0.0,
                "biomass": 663.4,
                "coal": 2420.0,
                "gas": 9135.2,
                "geothermal": 0.0,
                "hydro": 1014.2,
                "hydro storage": 0.0,
                "nuclear": 0.0,
                "oil": 66.0,
                "solar": 4008.3,
                "unknown": 0.0,
                "wind": 5499.5
            },
            "co2intensity": 505.51,
            "co2intensityProduction": 508.7,
            "countryCode": "IT-SO",
            "dischargeCo2Intensities": {
                "battery": 341.85417092564336,
                "hydro": 341.85417092564336
            },
            "dischargeCo2IntensitySources": {
                "battery": "electricityMap, 2021 average",
                "hydro": "electricityMap, 2021 average"
            },
            "estimationMethod": 0.0,
            "exchange": {
                "GR": 500.0,
                "IT-CSO": -2680.0,
                "IT-SIC": -144.0
            },
            "exchangeCapacities": {
                "GR": [
                    -500.0,
                    500.0
                ]
            },
            "exchangeCo2Intensities": {
                "GR": 474.09,
                "IT-CSO": 505.51,
                "IT-SIC": 505.51
            },
            "fossilFuelRatio": 0.8564,
            "fossilFuelRatioProduction": 0.8564,
            "maxCapacity": 9135.2,
            "maxDischarge": 0,
            "maxExport": 2680.0,
            "maxExportCapacity": 500.0,
            "maxImport": 500.0,
            "maxImportCapacity": 500.0,
            "maxProduction": 3059.0,
            "maxStorage": 0,
            "maxStorageCapacity": 0.0,
            "price": {
                "currency": "EUR",
                "value": 388.44
            },
            "production": {
                "biomass": 309.0,
                "coal": 995.0,
                "gas": 3059.0,
                "geothermal": 0.0,
                "hydro": 109.0,
                "nuclear": 0.0,
                "oil": 0.0,
                "solar": 3.0,
                "unknown": 155.0,
                "wind": 285.0
            },
            "productionCo2Intensities": {
                "biomass": 230,
                "coal": 820,
                "gas": 490,
                "geothermal": 38,
                "hydro": 24,
                "nuclear": 12,
                "oil": 650,
                "solar": 45,
                "unknown": 700,
                "wind": 11
            },
            "productionCo2IntensitySources": {
                "biomass": "IPCC 2014",
                "coal": "IPCC 2014",
                "gas": "IPCC 2014",
                "geothermal": "IPCC 2014",
                "hydro": "IPCC 2014",
                "nuclear": "IPCC 2014",
                "oil": "UK POST 2014",
                "solar": "IPCC 2014",
                "unknown": "assumes thermal (coal, gas, oil or biomass)",
                "wind": "IPCC 2014"
            },
            "renewableRatio": 0.1425,
            "renewableRatioProduction": 0.1436,
            "source": "entsoe.eu",
            "stateDatetime": "2022-07-11T23:00:00Z",
            "storage": {
                "battery": 0.0,
                "hydro": 0.0
            },
            "totalCo2Discharge": 0,
            "totalCo2Export": 1427560240.0,
            "totalCo2Import": 237045000.0,
            "totalCo2NetExchange": -1190515240.0,
            "totalCo2Production": 2500266000.0,
            "totalCo2Storage": 0,
            "totalConsumption": 2591.0,
            "totalDischarge": 0.0,
            "totalExport": 2824.0,
            "totalImport": 500.0,
            "totalProduction": 4915.0,
            "totalStorage": 0.0
        },
        {
            "_isFinestGranularity": true,
            "capacity": {
                "battery storage": 0.0,
                "biomass": 663.4,
                "coal": 2420.0,
                "gas": 9135.2,
                "geothermal": 0.0,
                "hydro": 1014.2,
                "hydro storage": 0.0,
                "nuclear": 0.0,
                "oil": 66.0,
                "solar": 4008.3,
                "unknown": 0.0,
                "wind": 5499.5
            },
            "co2intensity": 505.32,
            "co2intensityProduction": 508.89,
            "countryCode": "IT-SO",
            "dischargeCo2Intensities": {
                "battery": 341.85417092564336,
                "hydro": 341.85417092564336
            },
            "dischargeCo2IntensitySources": {
                "battery": "electricityMap, 2021 average",
                "hydro": "electricityMap, 2021 average"
            },
            "estimationMethod": 0.0,
            "exchange": {
                "GR": 500.0,
                "IT-CSO": -2879.0,
                "IT-SIC": 23.0
            },
            "exchangeCapacities": {
                "GR": [
                    -500.0,
                    500.0
                ]
            },
            "exchangeCo2Intensities": {
                "GR": 470.52,
                "IT-CSO": 505.32,
                "IT-SIC": 510.6
            },
            "fossilFuelRatio": 0.8534999999999999,
            "fossilFuelRatioProduction": 0.8531,
            "maxCapacity": 9135.2,
            "maxDischarge": 0,
            "maxExport": 2879.0,
            "maxExportCapacity": 500.0,
            "maxImport": 500.0,
            "maxImportCapacity": 500.0,
            "maxProduction": 2978.0,
            "maxStorage": 0,
            "maxStorageCapacity": 0.0,
            "price": {
                "currency": "EUR",
                "value": 365.31
            },
            "production": {
                "biomass": 312.0,
                "coal": 996.0,
                "gas": 2978.0,
                "geothermal": 0.0,
                "hydro": 109.0,
                "nuclear": 0.0,
                "oil": 0.0,
                "solar": 5.0,
                "unknown": 162.0,
                "wind": 286.0
            },
            "productionCo2Intensities": {
                "biomass": 230,
                "coal": 820,
                "gas": 490,
                "geothermal": 38,
                "hydro": 24,
                "nuclear": 12,
                "oil": 650,
                "solar": 45,
                "unknown": 700,
                "wind": 11
            },
            "productionCo2IntensitySources": {
                "biomass": "IPCC 2014",
                "coal": "IPCC 2014",
                "gas": "IPCC 2014",
                "geothermal": "IPCC 2014",
                "hydro": "IPCC 2014",
                "nuclear": "IPCC 2014",
                "oil": "UK POST 2014",
                "solar": "IPCC 2014",
                "unknown": "assumes thermal (coal, gas, oil or biomass)",
                "wind": "IPCC 2014"
            },
            "renewableRatio": 0.1456,
            "renewableRatioProduction": 0.1469,
            "source": "entsoe.eu",
            "stateDatetime": "2022-07-12T00:00:00Z",
            "storage": {
                "battery": 0.0,
                "hydro": 0.0
            },
            "totalCo2Discharge": 0,
            "totalCo2Export": 1454816280.0,
            "totalCo2Import": 247003800.0,
            "totalCo2NetExchange": -1207812480.0,
            "totalCo2Production": 2467087000.0,
            "totalCo2Storage": 0,
            "totalConsumption": 2492.0,
            "totalDischarge": 0.0,
            "totalExport": 2879.0,
            "totalImport": 523.0,
            "totalProduction": 4848.0,
            "totalStorage": 0.0
        },
        {
            "_isFinestGranularity": true,
            "capacity": {
                "battery storage": 0.0,
                "biomass": 663.4,
                "coal": 2420.0,
                "gas": 9135.2,
                "geothermal": 0.0,
                "hydro": 1014.2,
                "hydro storage": 0.0,
                "nuclear": 0.0,
                "oil": 66.0,
                "solar": 4008.3,
                "unknown": 0.0,
                "wind": 5499.5
            },
            "co2intensity": 503.48,
            "co2intensityProduction": 507.96,
            "countryCode": "IT-SO",
            "dischargeCo2Intensities": {
                "battery": 341.85417092564336,
                "hydro": 341.85417092564336
            },
            "dischargeCo2IntensitySources": {
                "battery": "electricityMap, 2021 average",
                "hydro": "electricityMap, 2021 average"
            },
            "estimationMethod": 0.0,
            "exchange": {
                "GR": 500.0,
                "IT-CSO": -2611.0,
                "IT-SIC": -48.0
            },
            "exchangeCapacities": {
                "GR": [
                    -500.0,
                    500.0
                ]
            },
            "exchangeCo2Intensities": {
                "GR": 462.57,
                "IT-CSO": 503.48,
                "IT-SIC": 503.48
            },
            "fossilFuelRatio": 0.8409,
            "fossilFuelRatioProduction": 0.8414,
            "maxCapacity": 9135.2,
            "maxDischarge": 0,
            "maxExport": 2611.0,
            "maxExportCapacity": 500.0,
            "maxImport": 500.0,
            "maxImportCapacity": 500.0,
            "maxProduction": 2697.0,
            "maxStorage": 0,
            "maxStorageCapacity": 0.0,
            "price": {
                "currency": "EUR",
                "value": 346.88
            },
            "production": {
                "biomass": 306.0,
                "coal": 995.0,
                "gas": 2697.0,
                "geothermal": 0.0,
                "hydro": 109.0,
                "nuclear": 0.0,
                "oil": 0.0,
                "solar": 7.0,
                "unknown": 154.0,
                "wind": 303.0
            },
            "productionCo2Intensities": {
                "biomass": 230,
                "coal": 820,
                "gas": 490,
                "geothermal": 38,
                "hydro": 24,
                "nuclear": 12,
                "oil": 650,
                "solar": 45,
                "unknown": 700,
                "wind": 11
            },
            "productionCo2IntensitySources": {
                "biomass": "IPCC 2014",
                "coal": "IPCC 2014",
                "gas": "IPCC 2014",
                "geothermal": "IPCC 2014",
                "hydro": "IPCC 2014",
                "nuclear": "IPCC 2014",
                "oil": "UK POST 2014",
                "solar": "IPCC 2014",
                "unknown": "assumes thermal (coal, gas, oil or biomass)",
                "wind": "IPCC 2014"
            },
            "renewableRatio": 0.1583,
            "renewableRatioProduction": 0.1586,
            "source": "entsoe.eu",
            "stateDatetime": "2022-07-12T01:00:00Z",
            "storage": {
                "battery": 0.0,
                "hydro": 0.0
            },
            "totalCo2Discharge": 0,
            "totalCo2Export": 1338753320.0,
            "totalCo2Import": 231285000.0,
            "totalCo2NetExchange": -1107468320.0,
            "totalCo2Production": 2321874000.0,
            "totalCo2Storage": 0,
            "totalConsumption": 2412.0,
            "totalDischarge": 0.0,
            "totalExport": 2659.0,
            "totalImport": 500.0,
            "totalProduction": 4571.0,
            "totalStorage": 0.0
        },
        {
            "_isFinestGranularity": true,
            "capacity": {
                "battery storage": 0.0,
                "biomass": 663.4,
                "coal": 2420.0,
                "gas": 9135.2,
                "geothermal": 0.0,
                "hydro": 1014.2,
                "hydro storage": 0.0,
                "nuclear": 0.0,
                "oil": 66.0,
                "solar": 4008.3,
                "unknown": 0.0,
                "wind": 5499.5
            },
            "co2intensity": 500.6,
            "co2intensityProduction": 506.44,
            "countryCode": "IT-SO",
            "dischargeCo2Intensities": {
                "battery": 341.85417092564336,
                "hydro": 341.85417092564336
            },
            "dischargeCo2IntensitySources": {
                "battery": "electricityMap, 2021 average",
                "hydro": "electricityMap, 2021 average"
            },
            "estimationMethod": 0.0,
            "exchange": {
                "GR": 500.0,
                "IT-CSO": -2624.0,
                "IT-SIC": -9.0
            },
            "exchangeCapacities": {
                "GR": [
                    -500.0,
                    500.0
                ]
            },
            "exchangeCo2Intensities": {
                "GR": 447.63,
                "IT-CSO": 500.6,
                "IT-SIC": 500.6
            },
            "fossilFuelRatio": 0.8332999999999999,
            "fossilFuelRatioProduction": 0.8362999999999999,
            "maxCapacity": 9135.2,
            "maxDischarge": 0,
            "maxExport": 2624.0,
            "maxExportCapacity": 500.0,
            "maxImport": 500.0,
            "maxImportCapacity": 500.0,
            "maxProduction": 2643.0,
            "maxStorage": 0,
            "maxStorageCapacity": 0.0,
            "price": {
                "currency": "EUR",
                "value": 341.5
            },
            "production": {
                "biomass": 309.0,
                "coal": 994.0,
                "gas": 2643.0,
                "geothermal": 0.0,
                "hydro": 116.0,
                "nuclear": 0.0,
                "oil": 0.0,
                "solar": 6.0,
                "unknown": 155.0,
                "wind": 311.0
            },
            "productionCo2Intensities": {
                "biomass": 230,
                "coal": 820,
                "gas": 490,
                "geothermal": 38,
                "hydro": 24,
                "nuclear": 12,
                "oil": 650,
                "solar": 45,
                "unknown": 700,
                "wind": 11
            },
            "productionCo2IntensitySources": {
                "biomass": "IPCC 2014",
                "coal": "IPCC 2014",
                "gas": "IPCC 2014",
                "geothermal": "IPCC 2014",
                "hydro": "IPCC 2014",
                "nuclear": "IPCC 2014",
                "oil": "UK POST 2014",
                "solar": "IPCC 2014",
                "unknown": "assumes thermal (coal, gas, oil or biomass)",
                "wind": "IPCC 2014"
            },
            "renewableRatio": 0.1659,
            "renewableRatioProduction": 0.1637,
            "source": "entsoe.eu",
            "stateDatetime": "2022-07-12T02:00:00Z",
            "storage": {
                "battery": 0.0,
                "hydro": 0.0
            },
            "totalCo2Discharge": 0,
            "totalCo2Export": 1318079800.0,
            "totalCo2Import": 223815000.0,
            "totalCo2NetExchange": -1094264800.0,
            "totalCo2Production": 2296195000.0,
            "totalCo2Storage": 0,
            "totalConsumption": 2401.0,
            "totalDischarge": 0.0,
            "totalExport": 2633.0,
            "totalImport": 500.0,
            "totalProduction": 4534.0,
            "totalStorage": 0.0
        },
        {
            "_isFinestGranularity": true,
            "capacity": {
                "battery storage": 0.0,
                "biomass": 663.4,
                "coal": 2420.0,
                "gas": 9135.2,
                "geothermal": 0.0,
                "hydro": 1014.2,
                "hydro storage": 0.0,
                "nuclear": 0.0,
                "oil": 66.0,
                "solar": 4008.3,
                "unknown": 0.0,
                "wind": 5499.5
            },
            "co2intensity": 487.86,
            "co2intensityProduction": 492.85,
            "countryCode": "IT-SO",
            "dischargeCo2Intensities": {
                "battery": 341.85417092564336,
                "hydro": 341.85417092564336
            },
            "dischargeCo2IntensitySources": {
                "battery": "electricityMap, 2021 average",
                "hydro": "electricityMap, 2021 average"
            },
            "estimationMethod": 0.0,
            "exchange": {
                "GR": 500.0,
                "IT-CSO": -3073.0,
                "IT-SIC": 67.0
            },
            "exchangeCapacities": {
                "GR": [
                    -500.0,
                    500.0
                ]
            },
            "exchangeCo2Intensities": {
                "GR": 434.98,
                "IT-CSO": 487.86,
                "IT-SIC": 511.81
            },
            "fossilFuelRatio": 0.823,
            "fossilFuelRatioProduction": 0.8253,
            "maxCapacity": 9135.2,
            "maxDischarge": 0,
            "maxExport": 3073.0,
            "maxExportCapacity": 500.0,
            "maxImport": 500.0,
            "maxImportCapacity": 500.0,
            "maxProduction": 2957.0,
            "maxStorage": 0,
            "maxStorageCapacity": 0.0,
            "price": {
                "currency": "EUR",
                "value": 362.1
            },
            "production": {
                "biomass": 307.0,
                "coal": 993.0,
                "gas": 2957.0,
                "geothermal": 0.0,
                "hydro": 190.0,
                "nuclear": 0.0,
                "oil": 0.0,
                "solar": 8.0,
                "unknown": 156.0,
                "wind": 364.0
            },
            "productionCo2Intensities": {
                "biomass": 230,
                "coal": 820,
                "gas": 490,
                "geothermal": 38,
                "hydro": 24,
                "nuclear": 12,
                "oil": 650,
                "solar": 45,
                "unknown": 700,
                "wind": 11
            },
            "productionCo2IntensitySources": {
                "biomass": "IPCC 2014",
                "coal": "IPCC 2014",
                "gas": "IPCC 2014",
                "geothermal": "IPCC 2014",
                "hydro": "IPCC 2014",
                "nuclear": "IPCC 2014",
                "oil": "UK POST 2014",
                "solar": "IPCC 2014",
                "unknown": "assumes thermal (coal, gas, oil or biomass)",
                "wind": "IPCC 2014"
            },
            "renewableRatio": 0.1766,
            "renewableRatioProduction": 0.1747,
            "source": "entsoe.eu",
            "stateDatetime": "2022-07-12T03:00:00Z",
            "storage": {
                "battery": 0.0,
                "hydro": 0.0
            },
            "totalCo2Discharge": 0,
            "totalCo2Export": 1499193780.0,
            "totalCo2Import": 251781270.0,
            "totalCo2NetExchange": -1247412510.0,
            "totalCo2Production": 2451924000.0,
            "totalCo2Storage": 0,
            "totalConsumption": 2469.0,
            "totalDischarge": 0.0,
            "totalExport": 3073.0,
            "totalImport": 567.0,
            "totalProduction": 4975.0,
            "totalStorage": 0.0
        },
        {
            "_isFinestGranularity": true,
            "capacity": {
                "battery storage": 0.0,
                "biomass": 663.4,
                "coal": 2420.0,
                "gas": 9135.2,
                "geothermal": 0.0,
                "hydro": 1014.2,
                "hydro storage": 0.0,
                "nuclear": 0.0,
                "oil": 66.0,
                "solar": 4008.3,
                "unknown": 0.0,
                "wind": 5499.5
            },
            "co2intensity": 481.06,
            "co2intensityProduction": 486.94,
            "countryCode": "IT-SO",
            "dischargeCo2Intensities": {
                "battery": 341.85417092564336,
                "hydro": 341.85417092564336
            },
            "dischargeCo2IntensitySources": {
                "battery": "electricityMap, 2021 average",
                "hydro": "electricityMap, 2021 average"
            },
            "estimationMethod": 0.0,
            "exchange": {
                "GR": 500.0,
                "IT-CSO": -3873.0,
                "IT-SIC": 87.0
            },
            "exchangeCapacities": {
                "GR": [
                    -500.0,
                    500.0
                ]
            },
            "exchangeCo2Intensities": {
                "GR": 407.04,
                "IT-CSO": 481.06,
                "IT-SIC": 502.6
            },
            "fossilFuelRatio": 0.8320000000000001,
            "fossilFuelRatioProduction": 0.8393,
            "maxCapacity": 9135.2,
            "maxDischarge": 0,
            "maxExport": 3873.0,
            "maxExportCapacity": 500.0,
            "maxImport": 500.0,
            "maxImportCapacity": 500.0,
            "maxProduction": 3837.0,
            "maxStorage": 0,
            "maxStorageCapacity": 0.0,
            "price": {
                "currency": "EUR",
                "value": 419.64
            },
            "production": {
                "biomass": 305.0,
                "coal": 996.0,
                "gas": 3837.0,
                "geothermal": 0.0,
                "hydro": 129.0,
                "nuclear": 0.0,
                "oil": 0.0,
                "solar": 189.0,
                "unknown": 181.0,
                "wind": 337.0
            },
            "productionCo2Intensities": {
                "biomass": 230,
                "coal": 820,
                "gas": 490,
                "geothermal": 38,
                "hydro": 24,
                "nuclear": 12,
                "oil": 650,
                "solar": 45,
                "unknown": 700,
                "wind": 11
            },
            "productionCo2IntensitySources": {
                "biomass": "IPCC 2014",
                "coal": "IPCC 2014",
                "gas": "IPCC 2014",
                "geothermal": "IPCC 2014",
                "hydro": "IPCC 2014",
                "nuclear": "IPCC 2014",
                "oil": "UK POST 2014",
                "solar": "IPCC 2014",
                "unknown": "assumes thermal (coal, gas, oil or biomass)",
                "wind": "IPCC 2014"
            },
            "renewableRatio": 0.1677,
            "renewableRatioProduction": 0.1607,
            "source": "entsoe.eu",
            "stateDatetime": "2022-07-12T04:00:00Z",
            "storage": {
                "battery": 0.0,
                "hydro": 0.0
            },
            "totalCo2Discharge": 0,
            "totalCo2Export": 1863145380.0,
            "totalCo2Import": 247246200.0,
            "totalCo2NetExchange": -1615899180.0,
            "totalCo2Production": 2909008000.0,
            "totalCo2Storage": 0,
            "totalConsumption": 2688.0,
            "totalDischarge": 0.0,
            "totalExport": 3873.0,
            "totalImport": 587.0,
            "totalProduction": 5974.0,
            "totalStorage": 0.0
        },
        {
            "_isFinestGranularity": true,
            "capacity": {
                "battery storage": 0.0,
                "biomass": 663.4,
                "coal": 2420.0,
                "gas": 9135.2,
                "geothermal": 0.0,
                "hydro": 1014.2,
                "hydro storage": 0.0,
                "nuclear": 0.0,
                "oil": 66.0,
                "solar": 4008.3,
                "unknown": 0.0,
                "wind": 5499.5
            },
            "co2intensity": 442.65,
            "co2intensityProduction": 447.44,
            "countryCode": "IT-SO",
            "dischargeCo2Intensities": {
                "battery": 341.85417092564336,
                "hydro": 341.85417092564336
            },
            "dischargeCo2IntensitySources": {
                "battery": "electricityMap, 2021 average",
                "hydro": "electricityMap, 2021 average"
            },
            "estimationMethod": 0.0,
            "exchange": {
                "GR": 500.0,
                "IT-CSO": -3958.0,
                "IT-SIC": -26.0
            },
            "exchangeCapacities": {
                "GR": [
                    -500.0,
                    500.0
                ]
            },
            "exchangeCo2Intensities": {
                "GR": 378.88,
                "IT-CSO": 442.65,
                "IT-SIC": 442.65
            },
            "fossilFuelRatio": 0.7589,
            "fossilFuelRatioProduction": 0.7652,
            "maxCapacity": 9135.2,
            "maxDischarge": 0,
            "maxExport": 3958.0,
            "maxExportCapacity": 500.0,
            "maxImport": 500.0,
            "maxImportCapacity": 500.0,
            "maxProduction": 3897.0,
            "maxStorage": 0,
            "maxStorageCapacity": 0.0,
            "price": {
                "currency": "EUR",
                "value": 450.0
            },
            "production": {
                "biomass": 306.0,
                "coal": 989.0,
                "gas": 3897.0,
                "geothermal": 0.0,
                "hydro": 134.0,
                "nuclear": 0.0,
                "oil": 0.0,
                "solar": 825.0,
                "unknown": 197.0,
                "wind": 295.0
            },
            "productionCo2Intensities": {
                "biomass": 230,
                "coal": 820,
                "gas": 490,
                "geothermal": 38,
                "hydro": 24,
                "nuclear": 12,
                "oil": 650,
                "solar": 45,
                "unknown": 700,
                "wind": 11
            },
            "productionCo2IntensitySources": {
                "biomass": "IPCC 2014",
                "coal": "IPCC 2014",
                "gas": "IPCC 2014",
                "geothermal": "IPCC 2014",
                "hydro": "IPCC 2014",
                "nuclear": "IPCC 2014",
                "oil": "UK POST 2014",
                "solar": "IPCC 2014",
                "unknown": "assumes thermal (coal, gas, oil or biomass)",
                "wind": "IPCC 2014"
            },
            "renewableRatio": 0.24100000000000002,
            "renewableRatioProduction": 0.2348,
            "source": "entsoe.eu",
            "stateDatetime": "2022-07-12T05:00:00Z",
            "storage": {
                "battery": 0.0,
                "hydro": 0.0
            },
            "totalCo2Discharge": 0,
            "totalCo2Export": 1763517600.0,
            "totalCo2Import": 189440000.0,
            "totalCo2NetExchange": -1574077600.0,
            "totalCo2Production": 2972376000.0,
            "totalCo2Storage": 0,
            "totalConsumption": 3159.0,
            "totalDischarge": 0.0,
            "totalExport": 3984.0,
            "totalImport": 500.0,
            "totalProduction": 6643.0,
            "totalStorage": 0.0
        },
        {
            "_isFinestGranularity": true,
            "capacity": {
                "battery storage": 0.0,
                "biomass": 663.4,
                "coal": 2420.0,
                "gas": 9135.2,
                "geothermal": 0.0,
                "hydro": 1014.2,
                "hydro storage": 0.0,
                "nuclear": 0.0,
                "oil": 66.0,
                "solar": 4008.3,
                "unknown": 0.0,
                "wind": 5499.5
            },
            "co2intensity": 391.8,
            "co2intensityProduction": 394.42,
            "countryCode": "IT-SO",
            "dischargeCo2Intensities": {
                "battery": 341.85417092564336,
                "hydro": 341.85417092564336
            },
            "dischargeCo2IntensitySources": {
                "battery": "electricityMap, 2021 average",
                "hydro": "electricityMap, 2021 average"
            },
            "estimationMethod": 0.0,
            "exchange": {
                "GR": 500.0,
                "IT-CSO": -4140.0,
                "IT-SIC": -125.0
            },
            "exchangeCapacities": {
                "GR": [
                    -500.0,
                    500.0
                ]
            },
            "exchangeCo2Intensities": {
                "GR": 353.07,
                "IT-CSO": 391.8,
                "IT-SIC": 391.8
            },
            "fossilFuelRatio": 0.6667000000000001,
            "fossilFuelRatioProduction": 0.6697,
            "maxCapacity": 9135.2,
            "maxDischarge": 0,
            "maxExport": 4140.0,
            "maxExportCapacity": 500.0,
            "maxImport": 500.0,
            "maxImportCapacity": 500.0,
            "maxProduction": 3855.0,
            "maxStorage": 0,
            "maxStorageCapacity": 0.0,
            "price": {
                "currency": "EUR",
                "value": 434.73
            },
            "production": {
                "biomass": 307.0,
                "coal": 895.0,
                "gas": 3855.0,
                "geothermal": 0.0,
                "hydro": 185.0,
                "nuclear": 0.0,
                "oil": 0.0,
                "solar": 1634.0,
                "unknown": 202.0,
                "wind": 316.0
            },
            "productionCo2Intensities": {
                "biomass": 230,
                "coal": 820,
                "gas": 490,
                "geothermal": 38,
                "hydro": 24,
                "nuclear": 12,
                "oil": 650,
                "solar": 45,
                "unknown": 700,
                "wind": 11
            },
            "productionCo2IntensitySources": {
                "biomass": "IPCC 2014",
                "coal": "IPCC 2014",
                "gas": "IPCC 2014",
                "geothermal": "IPCC 2014",
                "hydro": "IPCC 2014",
                "nuclear": "IPCC 2014",
                "oil": "UK POST 2014",
                "solar": "IPCC 2014",
                "unknown": "assumes thermal (coal, gas, oil or biomass)",
                "wind": "IPCC 2014"
            },
            "renewableRatio": 0.3332,
            "renewableRatioProduction": 0.33030000000000004,
            "source": "entsoe.eu",
            "stateDatetime": "2022-07-12T06:00:00Z",
            "storage": {
                "battery": 0.0,
                "hydro": 0.0
            },
            "totalCo2Discharge": 0,
            "totalCo2Export": 1671027000.0,
            "totalCo2Import": 176535000.0,
            "totalCo2NetExchange": -1494492000.0,
            "totalCo2Production": 2916306000.0,
            "totalCo2Storage": 0,
            "totalConsumption": 3629.0,
            "totalDischarge": 0.0,
            "totalExport": 4265.0,
            "totalImport": 500.0,
            "totalProduction": 7394.0,
            "totalStorage": 0.0
        },
        {
            "_isFinestGranularity": true,
            "capacity": {
                "battery storage": 0.0,
                "biomass": 663.4,
                "coal": 2420.0,
                "gas": 9135.2,
                "geothermal": 0.0,
                "hydro": 1014.2,
                "hydro storage": 0.0,
                "nuclear": 0.0,
                "oil": 66.0,
                "solar": 4008.3,
                "unknown": 0.0,
                "wind": 5499.5
            },
            "co2intensity": 364.26,
            "co2intensityProduction": 367.05,
            "countryCode": "IT-SO",
            "dischargeCo2Intensities": {
                "battery": 341.85417092564336,
                "hydro": 341.85417092564336
            },
            "dischargeCo2IntensitySources": {
                "battery": "electricityMap, 2021 average",
                "hydro": "electricityMap, 2021 average"
            },
            "estimationMethod": 0.0,
            "exchange": {
                "GR": 500.0,
                "IT-CSO": -4357.0,
                "IT-SIC": -113.0
            },
            "exchangeCapacities": {
                "GR": [
                    -500.0,
                    500.0
                ]
            },
            "exchangeCo2Intensities": {
                "GR": 319.86,
                "IT-CSO": 364.26,
                "IT-SIC": 364.26
            },
            "fossilFuelRatio": 0.6078,
            "fossilFuelRatioProduction": 0.6129,
            "maxCapacity": 9135.2,
            "maxDischarge": 0,
            "maxExport": 4357.0,
            "maxExportCapacity": 500.0,
            "maxImport": 500.0,
            "maxImportCapacity": 500.0,
            "maxProduction": 3757.0,
            "maxStorage": 0,
            "maxStorageCapacity": 0.0,
            "price": {
                "currency": "EUR",
                "value": 433.49
            },
            "production": {
                "biomass": 310.0,
                "coal": 931.0,
                "gas": 3757.0,
                "geothermal": 0.0,
                "hydro": 93.0,
                "nuclear": 0.0,
                "oil": 0.0,
                "solar": 2355.0,
                "unknown": 197.0,
                "wind": 327.0
            },
            "productionCo2Intensities": {
                "biomass": 230,
                "coal": 820,
                "gas": 490,
                "geothermal": 38,
                "hydro": 24,
                "nuclear": 12,
                "oil": 650,
                "solar": 45,
                "unknown": 700,
                "wind": 11
            },
            "productionCo2IntensitySources": {
                "biomass": "IPCC 2014",
                "coal": "IPCC 2014",
                "gas": "IPCC 2014",
                "geothermal": "IPCC 2014",
                "hydro": "IPCC 2014",
                "nuclear": "IPCC 2014",
                "oil": "UK POST 2014",
                "solar": "IPCC 2014",
                "unknown": "assumes thermal (coal, gas, oil or biomass)",
                "wind": "IPCC 2014"
            },
            "renewableRatio": 0.3921,
            "renewableRatioProduction": 0.3871,
            "source": "entsoe.eu",
            "stateDatetime": "2022-07-12T07:00:00Z",
            "storage": {
                "battery": 0.0,
                "hydro": 0.0
            },
            "totalCo2Discharge": 0,
            "totalCo2Export": 1628242200.0,
            "totalCo2Import": 159930000.0,
            "totalCo2NetExchange": -1468312200.0,
            "totalCo2Production": 2925354000.0,
            "totalCo2Storage": 0,
            "totalConsumption": 4000.0,
            "totalDischarge": 0.0,
            "totalExport": 4470.0,
            "totalImport": 500.0,
            "totalProduction": 7970.0,
            "totalStorage": 0.0
        },
        {
            "_isFinestGranularity": true,
            "capacity": {
                "battery storage": 0.0,
                "biomass": 663.4,
                "coal": 2420.0,
                "gas": 9135.2,
                "geothermal": 0.0,
                "hydro": 1014.2,
                "hydro storage": 0.0,
                "nuclear": 0.0,
                "oil": 66.0,
                "solar": 4008.3,
                "unknown": 0.0,
                "wind": 5499.5
            },
            "co2intensity": 352.28,
            "co2intensityProduction": 354.6,
            "countryCode": "IT-SO",
            "dischargeCo2Intensities": {
                "battery": 341.85417092564336,
                "hydro": 341.85417092564336
            },
            "dischargeCo2IntensitySources": {
                "battery": "electricityMap, 2021 average",
                "hydro": "electricityMap, 2021 average"
            },
            "estimationMethod": 0.0,
            "exchange": {
                "GR": 500.0,
                "IT-CSO": -4708.0,
                "IT-SIC": -123.0
            },
            "exchangeCapacities": {
                "GR": [
                    -500.0,
                    500.0
                ]
            },
            "exchangeCo2Intensities": {
                "GR": 313.59,
                "IT-CSO": 352.28,
                "IT-SIC": 352.28
            },
            "fossilFuelRatio": 0.5809000000000001,
            "fossilFuelRatioProduction": 0.5847,
            "maxCapacity": 9135.2,
            "maxDischarge": 0,
            "maxExport": 4708.0,
            "maxExportCapacity": 500.0,
            "maxImport": 500.0,
            "maxImportCapacity": 500.0,
            "maxProduction": 3693.0,
            "maxStorage": 0,
            "maxStorageCapacity": 0.0,
            "price": {
                "currency": "EUR",
                "value": 424.24
            },
            "production": {
                "biomass": 309.0,
                "coal": 987.0,
                "gas": 3693.0,
                "geothermal": 0.0,
                "hydro": 83.0,
                "nuclear": 0.0,
                "oil": 0.0,
                "solar": 2767.0,
                "unknown": 196.0,
                "wind": 304.0
            },
            "productionCo2Intensities": {
                "biomass": 230,
                "coal": 820,
                "gas": 490,
                "geothermal": 38,
                "hydro": 24,
                "nuclear": 12,
                "oil": 650,
                "solar": 45,
                "unknown": 700,
                "wind": 11
            },
            "productionCo2IntensitySources": {
                "biomass": "IPCC 2014",
                "coal": "IPCC 2014",
                "gas": "IPCC 2014",
                "geothermal": "IPCC 2014",
                "hydro": "IPCC 2014",
                "nuclear": "IPCC 2014",
                "oil": "UK POST 2014",
                "solar": "IPCC 2014",
                "unknown": "assumes thermal (coal, gas, oil or biomass)",
                "wind": "IPCC 2014"
            },
            "renewableRatio": 0.4189,
            "renewableRatioProduction": 0.4153,
            "source": "entsoe.eu",
            "stateDatetime": "2022-07-12T08:00:00Z",
            "storage": {
                "battery": 0.0,
                "hydro": 0.0
            },
            "totalCo2Discharge": 0,
            "totalCo2Export": 1701864679.9999998,
            "totalCo2Import": 156795000.0,
            "totalCo2NetExchange": -1545069679.9999998,
            "totalCo2Production": 2957031000.0,
            "totalCo2Storage": 0,
            "totalConsumption": 4008.0,
            "totalDischarge": 0.0,
            "totalExport": 4831.0,
            "totalImport": 500.0,
            "totalProduction": 8339.0,
            "totalStorage": 0.0
        },
        {
            "_isFinestGranularity": true,
            "capacity": {
                "battery storage": 0.0,
                "biomass": 663.4,
                "coal": 2420.0,
                "gas": 9135.2,
                "geothermal": 0.0,
                "hydro": 1014.2,
                "hydro storage": 0.0,
                "nuclear": 0.0,
                "oil": 66.0,
                "solar": 4008.3,
                "unknown": 0.0,
                "wind": 5499.5
            },
            "co2intensity": 322.85,
            "co2intensityProduction": 323.59,
            "countryCode": "IT-SO",
            "dischargeCo2Intensities": {
                "battery": 341.85417092564336,
                "hydro": 341.85417092564336
            },
            "dischargeCo2IntensitySources": {
                "battery": "electricityMap, 2021 average",
                "hydro": "electricityMap, 2021 average"
            },
            "estimationMethod": "ESTIMATED_TIME_SLICER_AVERAGE",
            "exchange": {
                "GR": 500.0,
                "IT-CSO": -4708.0,
                "IT-SIC": -123.0
            },
            "exchangeCapacities": {
                "GR": [
                    -500.0,
                    500.0
                ]
            },
            "exchangeCo2Intensities": {
                "GR": 311.23,
                "IT-CSO": 322.85,
                "IT-SIC": 322.85
            },
            "fossilFuelRatio": 0.5207999999999999,
            "fossilFuelRatioProduction": 0.5214,
            "maxCapacity": 9135.2,
            "maxDischarge": 0,
            "maxExport": 4708.0,
            "maxExportCapacity": 500.0,
            "maxImport": 500.0,
            "maxImportCapacity": 500.0,
            "maxProduction": 2999.14,
            "maxStorage": 0,
            "maxStorageCapacity": 0.0,
            "price": {
                "currency": "EUR",
                "value": 406.0
            },
            "production": {
                "biomass": 289.71,
                "coal": 958.71,
                "gas": 2999.14,
                "geothermal": 0.0,
                "hydro": 56.29,
                "nuclear": 0.0,
                "oil": 0.69,
                "solar": 2378.86,
                "unknown": 173.57,
                "wind": 1068.14
            },
            "productionCo2Intensities": {
                "biomass": 230,
                "coal": 820,
                "gas": 490,
                "geothermal": 38,
                "hydro": 24,
                "nuclear": 12,
                "oil": 650,
                "solar": 45,
                "unknown": 700,
                "wind": 11
            },
            "productionCo2IntensitySources": {
                "biomass": "IPCC 2014",
                "coal": "IPCC 2014",
                "gas": "IPCC 2014",
                "geothermal": "IPCC 2014",
                "hydro": "IPCC 2014",
                "nuclear": "IPCC 2014",
                "oil": "UK POST 2014",
                "solar": "IPCC 2014",
                "unknown": "assumes thermal (coal, gas, oil or biomass)",
                "wind": "IPCC 2014"
            },
            "renewableRatio": 0.479,
            "renewableRatioProduction": 0.47859999999999997,
            "source": "electricityMap Estimation",
            "stateDatetime": "2022-07-12T09:00:00Z",
            "storage": {
                "battery": 0.0,
                "hydro": 0.0
            },
            "totalCo2Discharge": 0,
            "totalCo2Export": 1559688350.0,
            "totalCo2Import": 155615000.0,
            "totalCo2NetExchange": -1404073350.0,
            "totalCo2Production": 2564450800.0,
            "totalCo2Storage": 0,
            "totalConsumption": 3594.12,
            "totalDischarge": 0.0,
            "totalExport": 4831.0,
            "totalImport": 500.0,
            "totalProduction": 7925.12,
            "totalStorage": 0.0
        }
    ]
}